[
null,
{"id":1,"list":[{"code":211,"indent":0,"parameters":[0]},{"code":121,"indent":0,"parameters":[1,1,0]},{"code":0,"indent":0,"parameters":[]}],"name":"enter_closet","switchId":1,"trigger":0},
{"id":2,"list":[{"code":211,"indent":0,"parameters":[1]},{"code":121,"indent":0,"parameters":[1,1,1]},{"code":0,"indent":0,"parameters":[]}],"name":"leave_closet","switchId":1,"trigger":0},
{"id":3,"list":[{"code":230,"indent":0,"parameters":[60]},{"code":121,"indent":0,"parameters":[2,2,1]},{"code":0,"indent":0,"parameters":[]}],"name":"hide_mary","switchId":1,"trigger":2},
{"id":4,"list":[{"code":242,"indent":0,"parameters":[5]},{"code":223,"indent":0,"parameters":[[-255,-255,-255,0],1,false]},{"code":201,"indent":0,"parameters":[0,1,0,0,0,2]},{"code":223,"indent":0,"parameters":[[0,0,0,0],1,false]},{"code":117,"indent":0,"parameters":[7]},{"code":111,"indent":0,"parameters":[0,3,0]},{"code":121,"indent":1,"parameters":[3,3,1]},{"code":119,"indent":1,"parameters":["next"]},{"code":0,"indent":1,"parameters":[]},{"code":412,"indent":0,"parameters":[]},{"code":112,"indent":0,"parameters":[]},{"code":102,"indent":1,"parameters":[["Fuwamoco's push-ups","Nerissa's girl dinner","Biboo's ritual","Shiori's cleanup","Next"],-2,0,1,0]},{"code":402,"indent":1,"parameters":[0,"Fuwamoco's push-ups"]},{"code":112,"indent":2,"parameters":[]},{"code":102,"indent":3,"parameters":[["Easy","Normal","Hard","Very hard","Insane"],-2,0,1,0]},{"code":402,"indent":3,"parameters":[0,"Easy"]},{"code":122,"indent":4,"parameters":[10,10,0,0,1]},{"code":117,"indent":4,"parameters":[21]},{"code":0,"indent":4,"parameters":[]},{"code":402,"indent":3,"parameters":[1,"Normal"]},{"code":122,"indent":4,"parameters":[10,10,0,0,2]},{"code":117,"indent":4,"parameters":[21]},{"code":0,"indent":4,"parameters":[]},{"code":402,"indent":3,"parameters":[2,"Hard"]},{"code":122,"indent":4,"parameters":[10,10,0,0,3]},{"code":117,"indent":4,"parameters":[21]},{"code":0,"indent":4,"parameters":[]},{"code":402,"indent":3,"parameters":[3,"Very hard"]},{"code":122,"indent":4,"parameters":[10,10,0,0,4]},{"code":117,"indent":4,"parameters":[21]},{"code":0,"indent":4,"parameters":[]},{"code":402,"indent":3,"parameters":[4,"Insane"]},{"code":122,"indent":4,"parameters":[10,10,0,0,5]},{"code":117,"indent":4,"parameters":[21]},{"code":0,"indent":4,"parameters":[]},{"code":403,"indent":3,"parameters":[6,null]},{"code":113,"indent":4,"parameters":[]},{"code":0,"indent":4,"parameters":[]},{"code":404,"indent":3,"parameters":[]},{"code":0,"indent":3,"parameters":[]},{"code":413,"indent":2,"parameters":[]},{"code":0,"indent":2,"parameters":[]},{"code":402,"indent":1,"parameters":[1,"Nerissa's girl dinner"]},{"code":117,"indent":2,"parameters":[19]},{"code":0,"indent":2,"parameters":[]},{"code":402,"indent":1,"parameters":[2,"Biboo's ritual"]},{"code":112,"indent":2,"parameters":[]},{"code":102,"indent":3,"parameters":[["3 stones","4 stones","5 stones","6 stones","7 stones","8 stones"],-2,0,1,0]},{"code":402,"indent":3,"parameters":[0,"3 stones"]},{"code":122,"indent":4,"parameters":[10,10,0,0,3]},{"code":117,"indent":4,"parameters":[18]},{"code":0,"indent":4,"parameters":[]},{"code":402,"indent":3,"parameters":[1,"4 stones"]},{"code":122,"indent":4,"parameters":[10,10,0,0,4]},{"code":117,"indent":4,"parameters":[18]},{"code":0,"indent":4,"parameters":[]},{"code":402,"indent":3,"parameters":[2,"5 stones"]},{"code":122,"indent":4,"parameters":[10,10,0,0,5]},{"code":117,"indent":4,"parameters":[18]},{"code":0,"indent":4,"parameters":[]},{"code":402,"indent":3,"parameters":[3,"6 stones"]},{"code":122,"indent":4,"parameters":[10,10,0,0,6]},{"code":117,"indent":4,"parameters":[18]},{"code":0,"indent":4,"parameters":[]},{"code":402,"indent":3,"parameters":[4,"7 stones"]},{"code":122,"indent":4,"parameters":[10,10,0,0,7]},{"code":117,"indent":4,"parameters":[18]},{"code":0,"indent":4,"parameters":[]},{"code":402,"indent":3,"parameters":[5,"8 stones"]},{"code":122,"indent":4,"parameters":[10,10,0,0,8]},{"code":117,"indent":4,"parameters":[18]},{"code":0,"indent":4,"parameters":[]},{"code":403,"indent":3,"parameters":[6,null]},{"code":113,"indent":4,"parameters":[]},{"code":0,"indent":4,"parameters":[]},{"code":404,"indent":3,"parameters":[]},{"code":0,"indent":3,"parameters":[]},{"code":413,"indent":2,"parameters":[]},{"code":0,"indent":2,"parameters":[]},{"code":402,"indent":1,"parameters":[3,"Shiori's cleanup"]},{"code":117,"indent":2,"parameters":[20]},{"code":0,"indent":2,"parameters":[]},{"code":402,"indent":1,"parameters":[4,"Next"]},{"code":118,"indent":2,"parameters":["next"]},{"code":102,"indent":2,"parameters":[["Shiori chasing Biboo","Previous"],-2,0,1,0]},{"code":402,"indent":2,"parameters":[0,"Shiori chasing Biboo"]},{"code":117,"indent":3,"parameters":[39]},{"code":115,"indent":3,"parameters":[]},{"code":0,"indent":3,"parameters":[]},{"code":402,"indent":2,"parameters":[1,"Previous"]},{"code":0,"indent":3,"parameters":[]},{"code":403,"indent":2,"parameters":[6,null]},{"code":113,"indent":3,"parameters":[]},{"code":0,"indent":3,"parameters":[]},{"code":404,"indent":2,"parameters":[]},{"code":0,"indent":2,"parameters":[]},{"code":403,"indent":1,"parameters":[6,null]},{"code":113,"indent":2,"parameters":[]},{"code":0,"indent":2,"parameters":[]},{"code":404,"indent":1,"parameters":[]},{"code":0,"indent":1,"parameters":[]},{"code":413,"indent":0,"parameters":[]},{"code":354,"indent":0,"parameters":[]},{"code":0,"indent":0,"parameters":[]}],"name":"minigame_menu","switchId":3,"trigger":0},
{"id":5,"list":[{"code":111,"indent":0,"parameters":[1,2,0,5,2]},{"code":231,"indent":1,"parameters":[2,"shiori_minigame_base",0,0,138,44,100,100,255,0]},{"code":115,"indent":1,"parameters":[]},{"code":0,"indent":1,"parameters":[]},{"code":412,"indent":0,"parameters":[]},{"code":111,"indent":0,"parameters":[1,2,0,10,2]},{"code":231,"indent":1,"parameters":[2,"shiori_minigame_base",0,0,138,44,100,100,192,0]},{"code":115,"indent":1,"parameters":[]},{"code":0,"indent":1,"parameters":[]},{"code":412,"indent":0,"parameters":[]},{"code":111,"indent":0,"parameters":[1,2,0,15,2]},{"code":231,"indent":1,"parameters":[2,"shiori_minigame_base",0,0,138,44,100,100,128,0]},{"code":115,"indent":1,"parameters":[]},{"code":0,"indent":1,"parameters":[]},{"code":412,"indent":0,"parameters":[]},{"code":231,"indent":0,"parameters":[2,"shiori_minigame_base",0,0,138,44,100,100,64,0]},{"code":0,"indent":0,"parameters":[]}],"name":"shiori_minigame_show_base","switchId":1,"trigger":0},
{"id":6,"list":[{"code":122,"indent":0,"parameters":[7,7,0,2,1,4]},{"code":111,"indent":0,"parameters":[1,6,1,7,0]},{"code":122,"indent":1,"parameters":[7,7,0,0,0]},{"code":0,"indent":1,"parameters":[]},{"code":411,"indent":0,"parameters":[]},{"code":122,"indent":1,"parameters":[6,6,0,1,7]},{"code":0,"indent":1,"parameters":[]},{"code":412,"indent":0,"parameters":[]},{"code":0,"indent":0,"parameters":[]}],"name":"shiori_minigame_set_new_direction","switchId":1,"trigger":0},
{"id":7,"list":[{"code":122,"indent":0,"parameters":[1,1,0,0,0]},{"code":0,"indent":0,"parameters":[]}],"name":"message_system","switchId":1,"trigger":0},
{"id":8,"list":[{"code":122,"indent":0,"parameters":[1,1,0,0,1]},{"code":0,"indent":0,"parameters":[]}],"name":"message_shiori","switchId":1,"trigger":0},
{"id":9,"list":[{"code":122,"indent":0,"parameters":[1,1,0,0,2]},{"code":0,"indent":0,"parameters":[]}],"name":"message_nerissa","switchId":1,"trigger":0},
{"id":10,"list":[{"code":122,"indent":0,"parameters":[1,1,0,0,3]},{"code":0,"indent":0,"parameters":[]}],"name":"message_biboo","switchId":1,"trigger":0},
{"id":11,"list":[{"code":122,"indent":0,"parameters":[1,1,0,0,4]},{"code":0,"indent":0,"parameters":[]}],"name":"message_fuwawa","switchId":1,"trigger":0},
{"id":12,"list":[{"code":122,"indent":0,"parameters":[1,1,0,0,5]},{"code":0,"indent":0,"parameters":[]}],"name":"message_mococo","switchId":1,"trigger":0},
{"id":13,"list":[{"code":122,"indent":0,"parameters":[1,1,0,0,6]},{"code":0,"indent":0,"parameters":[]}],"name":"message_fuwamoco","switchId":1,"trigger":0},
{"id":14,"list":[{"code":122,"indent":0,"parameters":[4,4,0,0,148]},{"code":122,"indent":0,"parameters":[5,5,0,4,"345 - $gameVariables.value(10) * 30"]},{"code":231,"indent":0,"parameters":[5,"hanoi_stone_1",0,1,4,5,100,100,255,0]},{"code":122,"indent":0,"parameters":[4,4,2,0,10]},{"code":122,"indent":0,"parameters":[5,5,1,0,30]},{"code":231,"indent":0,"parameters":[6,"hanoi_stone_2",0,1,4,5,100,100,255,0]},{"code":122,"indent":0,"parameters":[4,4,2,0,11]},{"code":122,"indent":0,"parameters":[5,5,1,0,30]},{"code":231,"indent":0,"parameters":[7,"hanoi_stone_3",0,1,4,5,100,100,255,0]},{"code":111,"indent":0,"parameters":[1,10,0,4,1]},{"code":122,"indent":1,"parameters":[4,4,2,0,10]},{"code":122,"indent":1,"parameters":[5,5,1,0,30]},{"code":231,"indent":1,"parameters":[8,"hanoi_stone_4",0,1,4,5,100,100,255,0]},{"code":0,"indent":1,"parameters":[]},{"code":412,"indent":0,"parameters":[]},{"code":111,"indent":0,"parameters":[1,10,0,5,1]},{"code":122,"indent":1,"parameters":[4,4,2,0,11]},{"code":122,"indent":1,"parameters":[5,5,1,0,30]},{"code":231,"indent":1,"parameters":[9,"hanoi_stone_5",0,1,4,5,100,100,255,0]},{"code":0,"indent":1,"parameters":[]},{"code":412,"indent":0,"parameters":[]},{"code":111,"indent":0,"parameters":[1,10,0,6,1]},{"code":122,"indent":1,"parameters":[4,4,2,0,10]},{"code":122,"indent":1,"parameters":[5,5,1,0,30]},{"code":231,"indent":1,"parameters":[10,"hanoi_stone_6",0,1,4,5,100,100,255,0]},{"code":0,"indent":1,"parameters":[]},{"code":412,"indent":0,"parameters":[]},{"code":111,"indent":0,"parameters":[1,10,0,7,1]},{"code":122,"indent":1,"parameters":[4,4,2,0,11]},{"code":122,"indent":1,"parameters":[5,5,1,0,30]},{"code":231,"indent":1,"parameters":[11,"hanoi_stone_7",0,1,4,5,100,100,255,0]},{"code":0,"indent":1,"parameters":[]},{"code":412,"indent":0,"parameters":[]},{"code":111,"indent":0,"parameters":[1,10,0,8,1]},{"code":122,"indent":1,"parameters":[4,4,2,0,10]},{"code":122,"indent":1,"parameters":[5,5,1,0,30]},{"code":231,"indent":1,"parameters":[12,"hanoi_stone_8",0,1,4,5,100,100,255,0]},{"code":0,"indent":1,"parameters":[]},{"code":412,"indent":0,"parameters":[]},{"code":0,"indent":0,"parameters":[]}],"name":"hanoi_show_stones","switchId":1,"trigger":0},
{"id":15,"list":[{"code":235,"indent":0,"parameters":[13]},{"code":235,"indent":0,"parameters":[14]},{"code":235,"indent":0,"parameters":[15]},{"code":122,"indent":0,"parameters":[4,4,0,4,"157 - Math.floor($gameVariables.value(8) * 10.5) + $gameVariables.value(6) * 210"]},{"code":122,"indent":0,"parameters":[5,5,0,0,65]},{"code":250,"indent":0,"parameters":[{"name":"Cursor1","volume":90,"pitch":110,"pan":0}]},{"code":117,"indent":0,"parameters":[17]},{"code":0,"indent":0,"parameters":[]}],"name":"hanoi_pick_up_stone","switchId":1,"trigger":0},
{"id":16,"list":[{"code":235,"indent":0,"parameters":[13]},{"code":235,"indent":0,"parameters":[14]},{"code":235,"indent":0,"parameters":[15]},{"code":250,"indent":0,"parameters":[{"name":"Cursor1","volume":90,"pitch":90,"pan":0}]},{"code":111,"indent":0,"parameters":[1,6,1,7,5]},{"code":122,"indent":1,"parameters":[4,4,0,4,"157 - Math.floor($gameVariables.value(8) * 10.5) + $gameVariables.value(7) * 210"]},{"code":122,"indent":1,"parameters":[5,5,0,0,65]},{"code":117,"indent":1,"parameters":[17]},{"code":122,"indent":1,"parameters":[16,16,1,0,1]},{"code":0,"indent":1,"parameters":[]},{"code":412,"indent":0,"parameters":[]},{"code":122,"indent":0,"parameters":[4,4,0,4,"157 - Math.floor($gameVariables.value(8) * 10.5) + $gameVariables.value(7) * 210"]},{"code":122,"indent":0,"parameters":[5,5,0,4,"345 - $gameVariables.value(9) * 30"]},{"code":117,"indent":0,"parameters":[17]},{"code":0,"indent":0,"parameters":[]}],"name":"hanoi_put_down_stone","switchId":1,"trigger":0},
{"id":17,"list":[{"code":111,"indent":0,"parameters":[1,8,0,1,0]},{"code":232,"indent":1,"parameters":[5,0,0,1,4,5,100,100,255,0,30,true]},{"code":0,"indent":1,"parameters":[]},{"code":412,"indent":0,"parameters":[]},{"code":111,"indent":0,"parameters":[1,8,0,2,0]},{"code":232,"indent":1,"parameters":[6,0,0,1,4,5,100,100,255,0,30,true]},{"code":0,"indent":1,"parameters":[]},{"code":412,"indent":0,"parameters":[]},{"code":111,"indent":0,"parameters":[1,8,0,3,0]},{"code":232,"indent":1,"parameters":[7,0,0,1,4,5,100,100,255,0,30,true]},{"code":0,"indent":1,"parameters":[]},{"code":412,"indent":0,"parameters":[]},{"code":111,"indent":0,"parameters":[1,8,0,4,0]},{"code":232,"indent":1,"parameters":[8,0,0,1,4,5,100,100,255,0,30,true]},{"code":0,"indent":1,"parameters":[]},{"code":412,"indent":0,"parameters":[]},{"code":111,"indent":0,"parameters":[1,8,0,5,0]},{"code":232,"indent":1,"parameters":[9,0,0,1,4,5,100,100,255,0,30,true]},{"code":0,"indent":1,"parameters":[]},{"code":412,"indent":0,"parameters":[]},{"code":111,"indent":0,"parameters":[1,8,0,6,0]},{"code":232,"indent":1,"parameters":[10,0,0,1,4,5,100,100,255,0,30,true]},{"code":0,"indent":1,"parameters":[]},{"code":412,"indent":0,"parameters":[]},{"code":111,"indent":0,"parameters":[1,8,0,7,0]},{"code":232,"indent":1,"parameters":[11,0,0,1,4,5,100,100,255,0,30,true]},{"code":0,"indent":1,"parameters":[]},{"code":412,"indent":0,"parameters":[]},{"code":111,"indent":0,"parameters":[1,8,0,8,0]},{"code":232,"indent":1,"parameters":[12,0,0,1,4,5,100,100,255,0,30,true]},{"code":0,"indent":1,"parameters":[]},{"code":412,"indent":0,"parameters":[]},{"code":0,"indent":0,"parameters":[]}],"name":"hanoi_move_stone","switchId":1,"trigger":0},
{"id":18,"list":[{"code":122,"indent":0,"parameters":[16,16,0,0,0]},{"code":122,"indent":0,"parameters":[11,11,0,4,"(1 << $gameVariables.value(10)) - 1"]},{"code":122,"indent":0,"parameters":[6,6,0,0,-1]},{"code":122,"indent":0,"parameters":[7,7,0,0,-1]},{"code":121,"indent":0,"parameters":[9,9,1]},{"code":356,"indent":0,"parameters":["ILB7_HanoiTowers start \\V[10]"]},{"code":356,"indent":0,"parameters":["ILB7_NonBlockingMessageXY 0 500 center"]},{"code":356,"indent":0,"parameters":["ILB7_NonBlockingMessagePermanent Press ESC to reset the puzzle or receive a hint."]},{"code":231,"indent":0,"parameters":[1,"3",0,0,48,12,100,100,255,0]},{"code":231,"indent":0,"parameters":[2,"hanoi_stand",0,0,123,345,100,100,255,0]},{"code":231,"indent":0,"parameters":[3,"hanoi_stand",0,0,333,345,100,100,255,0]},{"code":231,"indent":0,"parameters":[4,"hanoi_stand",0,0,543,345,100,100,255,0]},{"code":117,"indent":0,"parameters":[14]},{"code":356,"indent":0,"parameters":["MessageRows 5"]},{"code":101,"indent":0,"parameters":["",0,1,1]},{"code":401,"indent":0,"parameters":["Move all stones to the rightmost stand."]},{"code":401,"indent":0,"parameters":["There are only two rules:"]},{"code":401,"indent":0,"parameters":[" 1. You can't put a bigger stone on top of"]},{"code":401,"indent":0,"parameters":["    a smaller one."]},{"code":101,"indent":0,"parameters":["",0,1,1]},{"code":401,"indent":0,"parameters":[" 2. You can only move one stone at a time."]},{"code":356,"indent":0,"parameters":["MessageRows 4"]},{"code":356,"indent":0,"parameters":["ILB7_Timer start"]},{"code":112,"indent":0,"parameters":[]},{"code":111,"indent":1,"parameters":[0,8,0]},{"code":113,"indent":2,"parameters":[]},{"code":0,"indent":2,"parameters":[]},{"code":412,"indent":1,"parameters":[]},{"code":111,"indent":1,"parameters":[11,"cancel"]},{"code":102,"indent":2,"parameters":[["Reset","Hint #1","Hint #2","Hint #3","My brain melted; can I please skip this puzzle?","Go back"],5,0,1,0]},{"code":402,"indent":2,"parameters":[0,"Reset"]},{"code":101,"indent":3,"parameters":["",0,1,1]},{"code":401,"indent":3,"parameters":["Are you sure you want to reset this minigame?"]},{"code":102,"indent":3,"parameters":[["Yes","No"],1,0,1,0]},{"code":402,"indent":3,"parameters":[0,"Yes"]},{"code":235,"indent":4,"parameters":[13]},{"code":235,"indent":4,"parameters":[14]},{"code":235,"indent":4,"parameters":[15]},{"code":122,"indent":4,"parameters":[16,16,0,0,0]},{"code":122,"indent":4,"parameters":[6,6,0,0,-1]},{"code":122,"indent":4,"parameters":[7,7,0,0,-1]},{"code":121,"indent":4,"parameters":[9,9,1]},{"code":356,"indent":4,"parameters":["ILB7_HanoiTowers start \\V[10]"]},{"code":117,"indent":4,"parameters":[14]},{"code":356,"indent":4,"parameters":["ILB7_Timer start"]},{"code":0,"indent":4,"parameters":[]},{"code":402,"indent":3,"parameters":[1,"No"]},{"code":0,"indent":4,"parameters":[]},{"code":404,"indent":3,"parameters":[]},{"code":0,"indent":3,"parameters":[]},{"code":402,"indent":2,"parameters":[1,"Hint #1"]},{"code":101,"indent":3,"parameters":["",0,1,1]},{"code":401,"indent":3,"parameters":["Begin by moving the two smallest stones to the"]},{"code":401,"indent":3,"parameters":["rightmost stack."]},{"code":231,"indent":3,"parameters":[16,"hanoi_hint_1",0,0,108,162,100,100,255,0]},{"code":230,"indent":3,"parameters":[30]},{"code":112,"indent":3,"parameters":[]},{"code":111,"indent":4,"parameters":[11,"ok"]},{"code":235,"indent":5,"parameters":[16]},{"code":113,"indent":5,"parameters":[]},{"code":0,"indent":5,"parameters":[]},{"code":412,"indent":4,"parameters":[]},{"code":0,"indent":4,"parameters":[]},{"code":413,"indent":3,"parameters":[]},{"code":0,"indent":3,"parameters":[]},{"code":402,"indent":2,"parameters":[2,"Hint #2"]},{"code":101,"indent":3,"parameters":["",0,1,1]},{"code":401,"indent":3,"parameters":["Continue by moving the third stone to the middle stack"]},{"code":401,"indent":3,"parameters":["and placing the two smallest stones on top of it the"]},{"code":401,"indent":3,"parameters":["same way as you moved them to the rightmost stack."]},{"code":231,"indent":3,"parameters":[16,"hanoi_hint_2",0,0,108,162,100,100,255,0]},{"code":230,"indent":3,"parameters":[30]},{"code":112,"indent":3,"parameters":[]},{"code":111,"indent":4,"parameters":[11,"ok"]},{"code":235,"indent":5,"parameters":[16]},{"code":113,"indent":5,"parameters":[]},{"code":0,"indent":5,"parameters":[]},{"code":412,"indent":4,"parameters":[]},{"code":0,"indent":4,"parameters":[]},{"code":413,"indent":3,"parameters":[]},{"code":0,"indent":3,"parameters":[]},{"code":402,"indent":2,"parameters":[3,"Hint #3"]},{"code":101,"indent":3,"parameters":["",0,1,1]},{"code":401,"indent":3,"parameters":["Continue by moving the biggest stone to the rightmost"]},{"code":401,"indent":3,"parameters":["stack and moving the two smallest stones to the"]},{"code":401,"indent":3,"parameters":["leftmost one."]},{"code":231,"indent":3,"parameters":[16,"hanoi_hint_3",0,0,108,162,100,100,255,0]},{"code":230,"indent":3,"parameters":[30]},{"code":112,"indent":3,"parameters":[]},{"code":111,"indent":4,"parameters":[11,"ok"]},{"code":235,"indent":5,"parameters":[16]},{"code":113,"indent":5,"parameters":[]},{"code":0,"indent":5,"parameters":[]},{"code":412,"indent":4,"parameters":[]},{"code":0,"indent":4,"parameters":[]},{"code":413,"indent":3,"parameters":[]},{"code":0,"indent":3,"parameters":[]},{"code":402,"indent":2,"parameters":[4,"My brain melted; can I please skip this puzzle?"]},{"code":101,"indent":3,"parameters":["",0,1,1]},{"code":401,"indent":3,"parameters":["Are you sure you want to skip this minigame?"]},{"code":102,"indent":3,"parameters":[["Yes","No"],1,0,1,0]},{"code":402,"indent":3,"parameters":[0,"Yes"]},{"code":119,"indent":4,"parameters":["skipped"]},{"code":0,"indent":4,"parameters":[]},{"code":402,"indent":3,"parameters":[1,"No"]},{"code":0,"indent":4,"parameters":[]},{"code":404,"indent":3,"parameters":[]},{"code":0,"indent":3,"parameters":[]},{"code":402,"indent":2,"parameters":[5,"Go back"]},{"code":0,"indent":3,"parameters":[]},{"code":404,"indent":2,"parameters":[]},{"code":0,"indent":2,"parameters":[]},{"code":412,"indent":1,"parameters":[]},{"code":111,"indent":1,"parameters":[0,5,0]},{"code":231,"indent":2,"parameters":[13,"key_left",0,0,151,20,100,100,255,0]},{"code":111,"indent":2,"parameters":[11,"left"]},{"code":356,"indent":3,"parameters":["ILB7_HanoiTowers pick 0"]},{"code":111,"indent":3,"parameters":[0,9,0]},{"code":121,"indent":4,"parameters":[9,9,1]},{"code":122,"indent":4,"parameters":[7,7,0,0,0]},{"code":117,"indent":4,"parameters":[16]},{"code":0,"indent":4,"parameters":[]},{"code":411,"indent":3,"parameters":[]},{"code":121,"indent":4,"parameters":[9,9,0]},{"code":122,"indent":4,"parameters":[6,6,0,0,0]},{"code":117,"indent":4,"parameters":[15]},{"code":0,"indent":4,"parameters":[]},{"code":412,"indent":3,"parameters":[]},{"code":0,"indent":3,"parameters":[]},{"code":412,"indent":2,"parameters":[]},{"code":0,"indent":2,"parameters":[]},{"code":412,"indent":1,"parameters":[]},{"code":111,"indent":1,"parameters":[0,6,0]},{"code":231,"indent":2,"parameters":[14,"key_up",0,0,371,20,100,100,255,0]},{"code":121,"indent":2,"parameters":[10,10,1]},{"code":111,"indent":2,"parameters":[11,"up"]},{"code":121,"indent":3,"parameters":[10,10,0]},{"code":0,"indent":3,"parameters":[]},{"code":412,"indent":2,"parameters":[]},{"code":111,"indent":2,"parameters":[11,"down"]},{"code":121,"indent":3,"parameters":[10,10,0]},{"code":0,"indent":3,"parameters":[]},{"code":412,"indent":2,"parameters":[]},{"code":111,"indent":2,"parameters":[0,10,0]},{"code":356,"indent":3,"parameters":["ILB7_HanoiTowers pick 1"]},{"code":111,"indent":3,"parameters":[0,9,0]},{"code":121,"indent":4,"parameters":[9,9,1]},{"code":122,"indent":4,"parameters":[7,7,0,0,1]},{"code":117,"indent":4,"parameters":[16]},{"code":0,"indent":4,"parameters":[]},{"code":411,"indent":3,"parameters":[]},{"code":121,"indent":4,"parameters":[9,9,0]},{"code":122,"indent":4,"parameters":[6,6,0,0,1]},{"code":117,"indent":4,"parameters":[15]},{"code":0,"indent":4,"parameters":[]},{"code":412,"indent":3,"parameters":[]},{"code":0,"indent":3,"parameters":[]},{"code":412,"indent":2,"parameters":[]},{"code":0,"indent":2,"parameters":[]},{"code":412,"indent":1,"parameters":[]},{"code":111,"indent":1,"parameters":[0,7,0]},{"code":231,"indent":2,"parameters":[15,"key_right",0,0,591,20,100,100,255,0]},{"code":111,"indent":2,"parameters":[11,"right"]},{"code":356,"indent":3,"parameters":["ILB7_HanoiTowers pick 2"]},{"code":111,"indent":3,"parameters":[0,9,0]},{"code":121,"indent":4,"parameters":[9,9,1]},{"code":122,"indent":4,"parameters":[7,7,0,0,2]},{"code":117,"indent":4,"parameters":[16]},{"code":0,"indent":4,"parameters":[]},{"code":411,"indent":3,"parameters":[]},{"code":121,"indent":4,"parameters":[9,9,0]},{"code":122,"indent":4,"parameters":[6,6,0,0,2]},{"code":117,"indent":4,"parameters":[15]},{"code":0,"indent":4,"parameters":[]},{"code":412,"indent":3,"parameters":[]},{"code":0,"indent":3,"parameters":[]},{"code":412,"indent":2,"parameters":[]},{"code":0,"indent":2,"parameters":[]},{"code":412,"indent":1,"parameters":[]},{"code":0,"indent":1,"parameters":[]},{"code":413,"indent":0,"parameters":[]},{"code":356,"indent":0,"parameters":["ILB7_Timer stop"]},{"code":250,"indent":0,"parameters":[{"name":"Applause1","volume":90,"pitch":100,"pan":0}]},{"code":101,"indent":0,"parameters":["",0,1,1]},{"code":401,"indent":0,"parameters":["Done! You completed the puzzle in \\V[16] moves!"]},{"code":401,"indent":0,"parameters":["The optimal solution is \\V[11] moves!"]},{"code":401,"indent":0,"parameters":["Your time: \\V[25]"]},{"code":118,"indent":0,"parameters":["skipped"]},{"code":356,"indent":0,"parameters":["ILB7_NonBlockingMessageClose"]},{"code":235,"indent":0,"parameters":[1]},{"code":235,"indent":0,"parameters":[2]},{"code":235,"indent":0,"parameters":[3]},{"code":235,"indent":0,"parameters":[4]},{"code":235,"indent":0,"parameters":[5]},{"code":235,"indent":0,"parameters":[6]},{"code":235,"indent":0,"parameters":[7]},{"code":235,"indent":0,"parameters":[8]},{"code":235,"indent":0,"parameters":[9]},{"code":235,"indent":0,"parameters":[10]},{"code":235,"indent":0,"parameters":[11]},{"code":235,"indent":0,"parameters":[12]},{"code":235,"indent":0,"parameters":[13]},{"code":235,"indent":0,"parameters":[14]},{"code":235,"indent":0,"parameters":[15]},{"code":0,"indent":0,"parameters":[]}],"name":"hanoi_minigame","switchId":1,"trigger":0},
{"id":19,"list":[{"code":122,"indent":0,"parameters":[2,2,0,0,0]},{"code":122,"indent":0,"parameters":[3,3,0,0,0]},{"code":122,"indent":0,"parameters":[4,4,0,0,250]},{"code":122,"indent":0,"parameters":[5,5,0,0,0]},{"code":231,"indent":0,"parameters":[1,"girl_dinner",0,0,48,12,100,100,255,0]},{"code":231,"indent":0,"parameters":[2,"spoon",0,1,4,5,100,100,255,0]},{"code":101,"indent":0,"parameters":["",0,1,1]},{"code":401,"indent":0,"parameters":["Stir the soup according to the onscreen directions."]},{"code":356,"indent":0,"parameters":["ILB7_Timer start"]},{"code":112,"indent":0,"parameters":[]},{"code":111,"indent":1,"parameters":[11,"cancel"]},{"code":101,"indent":2,"parameters":["",0,1,1]},{"code":401,"indent":2,"parameters":["Are you sure you want to skip this minigame?"]},{"code":102,"indent":2,"parameters":[["Yes","No"],1,0,1,0]},{"code":402,"indent":2,"parameters":[0,"Yes"]},{"code":119,"indent":3,"parameters":["skipped"]},{"code":0,"indent":3,"parameters":[]},{"code":402,"indent":2,"parameters":[1,"No"]},{"code":0,"indent":3,"parameters":[]},{"code":404,"indent":2,"parameters":[]},{"code":0,"indent":2,"parameters":[]},{"code":412,"indent":1,"parameters":[]},{"code":111,"indent":1,"parameters":[1,3,0,0,0]},{"code":231,"indent":2,"parameters":[3,"key_right",0,0,700,300,100,100,255,0]},{"code":111,"indent":2,"parameters":[11,"right"]},{"code":235,"indent":3,"parameters":[3]},{"code":250,"indent":3,"parameters":[{"name":"Pollen","volume":90,"pitch":100,"pan":0}]},{"code":122,"indent":3,"parameters":[4,4,1,0,200]},{"code":232,"indent":3,"parameters":[2,0,0,1,4,5,100,100,255,0,30,true]},{"code":122,"indent":3,"parameters":[3,3,1,0,1]},{"code":0,"indent":3,"parameters":[]},{"code":412,"indent":2,"parameters":[]},{"code":0,"indent":2,"parameters":[]},{"code":412,"indent":1,"parameters":[]},{"code":111,"indent":1,"parameters":[1,3,0,1,0]},{"code":231,"indent":2,"parameters":[3,"key_down",0,0,385,565,100,100,255,0]},{"code":111,"indent":2,"parameters":[11,"down"]},{"code":235,"indent":3,"parameters":[3]},{"code":250,"indent":3,"parameters":[{"name":"Pollen","volume":90,"pitch":100,"pan":0}]},{"code":122,"indent":3,"parameters":[5,5,1,0,200]},{"code":232,"indent":3,"parameters":[2,0,0,1,4,5,100,100,255,0,30,true]},{"code":122,"indent":3,"parameters":[3,3,1,0,1]},{"code":0,"indent":3,"parameters":[]},{"code":412,"indent":2,"parameters":[]},{"code":0,"indent":2,"parameters":[]},{"code":412,"indent":1,"parameters":[]},{"code":111,"indent":1,"parameters":[1,3,0,2,0]},{"code":231,"indent":2,"parameters":[3,"key_left",0,0,55,300,100,100,255,0]},{"code":111,"indent":2,"parameters":[11,"left"]},{"code":235,"indent":3,"parameters":[3]},{"code":250,"indent":3,"parameters":[{"name":"Pollen","volume":90,"pitch":100,"pan":0}]},{"code":122,"indent":3,"parameters":[4,4,2,0,200]},{"code":232,"indent":3,"parameters":[2,0,0,1,4,5,100,100,255,0,30,true]},{"code":122,"indent":3,"parameters":[3,3,1,0,1]},{"code":0,"indent":3,"parameters":[]},{"code":412,"indent":2,"parameters":[]},{"code":0,"indent":2,"parameters":[]},{"code":412,"indent":1,"parameters":[]},{"code":111,"indent":1,"parameters":[1,3,0,3,0]},{"code":231,"indent":2,"parameters":[3,"key_up",0,0,385,20,100,100,255,0]},{"code":111,"indent":2,"parameters":[11,"up"]},{"code":235,"indent":3,"parameters":[3]},{"code":250,"indent":3,"parameters":[{"name":"Pollen","volume":90,"pitch":100,"pan":0}]},{"code":122,"indent":3,"parameters":[5,5,2,0,200]},{"code":232,"indent":3,"parameters":[2,0,0,1,4,5,100,100,255,0,30,true]},{"code":122,"indent":3,"parameters":[2,2,1,0,1]},{"code":122,"indent":3,"parameters":[3,3,0,0,0]},{"code":0,"indent":3,"parameters":[]},{"code":412,"indent":2,"parameters":[]},{"code":0,"indent":2,"parameters":[]},{"code":412,"indent":1,"parameters":[]},{"code":111,"indent":1,"parameters":[1,2,0,3,0]},{"code":122,"indent":2,"parameters":[2,2,0,0,0]},{"code":113,"indent":2,"parameters":[]},{"code":0,"indent":2,"parameters":[]},{"code":412,"indent":1,"parameters":[]},{"code":0,"indent":1,"parameters":[]},{"code":413,"indent":0,"parameters":[]},{"code":112,"indent":0,"parameters":[]},{"code":111,"indent":1,"parameters":[1,3,0,1,0]},{"code":231,"indent":2,"parameters":[3,"key_right",0,0,700,300,100,100,255,0]},{"code":111,"indent":2,"parameters":[11,"right"]},{"code":235,"indent":3,"parameters":[3]},{"code":250,"indent":3,"parameters":[{"name":"Pollen","volume":90,"pitch":100,"pan":0}]},{"code":122,"indent":3,"parameters":[4,4,1,0,200]},{"code":232,"indent":3,"parameters":[2,0,0,1,4,5,100,100,255,0,30,true]},{"code":122,"indent":3,"parameters":[3,3,1,0,1]},{"code":0,"indent":3,"parameters":[]},{"code":412,"indent":2,"parameters":[]},{"code":0,"indent":2,"parameters":[]},{"code":412,"indent":1,"parameters":[]},{"code":111,"indent":1,"parameters":[1,3,0,0,0]},{"code":231,"indent":2,"parameters":[3,"key_down",0,0,385,565,100,100,255,0]},{"code":111,"indent":2,"parameters":[11,"down"]},{"code":235,"indent":3,"parameters":[3]},{"code":250,"indent":3,"parameters":[{"name":"Pollen","volume":90,"pitch":100,"pan":0}]},{"code":122,"indent":3,"parameters":[5,5,1,0,200]},{"code":232,"indent":3,"parameters":[2,0,0,1,4,5,100,100,255,0,30,true]},{"code":122,"indent":3,"parameters":[3,3,1,0,1]},{"code":0,"indent":3,"parameters":[]},{"code":412,"indent":2,"parameters":[]},{"code":0,"indent":2,"parameters":[]},{"code":412,"indent":1,"parameters":[]},{"code":111,"indent":1,"parameters":[1,3,0,3,0]},{"code":231,"indent":2,"parameters":[3,"key_left",0,0,55,300,100,100,255,0]},{"code":111,"indent":2,"parameters":[11,"left"]},{"code":235,"indent":3,"parameters":[3]},{"code":250,"indent":3,"parameters":[{"name":"Pollen","volume":90,"pitch":100,"pan":0}]},{"code":122,"indent":3,"parameters":[4,4,2,0,200]},{"code":232,"indent":3,"parameters":[2,0,0,1,4,5,100,100,255,0,30,true]},{"code":122,"indent":3,"parameters":[3,3,0,0,0]},{"code":122,"indent":3,"parameters":[2,2,1,0,1]},{"code":0,"indent":3,"parameters":[]},{"code":412,"indent":2,"parameters":[]},{"code":0,"indent":2,"parameters":[]},{"code":412,"indent":1,"parameters":[]},{"code":111,"indent":1,"parameters":[1,3,0,2,0]},{"code":231,"indent":2,"parameters":[3,"key_up",0,0,385,20,100,100,255,0]},{"code":111,"indent":2,"parameters":[11,"up"]},{"code":235,"indent":3,"parameters":[3]},{"code":250,"indent":3,"parameters":[{"name":"Pollen","volume":90,"pitch":100,"pan":0}]},{"code":122,"indent":3,"parameters":[5,5,2,0,200]},{"code":232,"indent":3,"parameters":[2,0,0,1,4,5,100,100,255,0,30,true]},{"code":122,"indent":3,"parameters":[3,3,1,0,1]},{"code":0,"indent":3,"parameters":[]},{"code":412,"indent":2,"parameters":[]},{"code":0,"indent":2,"parameters":[]},{"code":412,"indent":1,"parameters":[]},{"code":111,"indent":1,"parameters":[1,2,0,3,0]},{"code":122,"indent":2,"parameters":[2,2,0,0,0]},{"code":113,"indent":2,"parameters":[]},{"code":0,"indent":2,"parameters":[]},{"code":412,"indent":1,"parameters":[]},{"code":0,"indent":1,"parameters":[]},{"code":413,"indent":0,"parameters":[]},{"code":112,"indent":0,"parameters":[]},{"code":111,"indent":1,"parameters":[1,3,0,0,0]},{"code":231,"indent":2,"parameters":[3,"key_right",0,0,700,300,100,100,255,0]},{"code":111,"indent":2,"parameters":[11,"right"]},{"code":235,"indent":3,"parameters":[3]},{"code":250,"indent":3,"parameters":[{"name":"Pollen","volume":90,"pitch":100,"pan":0}]},{"code":122,"indent":3,"parameters":[4,4,1,0,200]},{"code":232,"indent":3,"parameters":[2,0,0,1,4,5,100,100,255,0,30,true]},{"code":122,"indent":3,"parameters":[3,3,1,0,1]},{"code":0,"indent":3,"parameters":[]},{"code":412,"indent":2,"parameters":[]},{"code":0,"indent":2,"parameters":[]},{"code":412,"indent":1,"parameters":[]},{"code":111,"indent":1,"parameters":[1,3,0,1,0]},{"code":231,"indent":2,"parameters":[3,"key_down",0,0,385,565,100,100,255,0]},{"code":111,"indent":2,"parameters":[11,"down"]},{"code":235,"indent":3,"parameters":[3]},{"code":250,"indent":3,"parameters":[{"name":"Pollen","volume":90,"pitch":100,"pan":0}]},{"code":122,"indent":3,"parameters":[5,5,1,0,200]},{"code":232,"indent":3,"parameters":[2,0,0,1,4,5,100,100,255,0,30,true]},{"code":122,"indent":3,"parameters":[3,3,1,0,1]},{"code":0,"indent":3,"parameters":[]},{"code":412,"indent":2,"parameters":[]},{"code":0,"indent":2,"parameters":[]},{"code":412,"indent":1,"parameters":[]},{"code":111,"indent":1,"parameters":[1,3,0,2,0]},{"code":231,"indent":2,"parameters":[3,"key_left",0,0,55,300,100,100,255,0]},{"code":111,"indent":2,"parameters":[11,"left"]},{"code":235,"indent":3,"parameters":[3]},{"code":250,"indent":3,"parameters":[{"name":"Pollen","volume":90,"pitch":100,"pan":0}]},{"code":122,"indent":3,"parameters":[4,4,2,0,200]},{"code":232,"indent":3,"parameters":[2,0,0,1,4,5,100,100,255,0,30,true]},{"code":122,"indent":3,"parameters":[3,3,1,0,1]},{"code":0,"indent":3,"parameters":[]},{"code":412,"indent":2,"parameters":[]},{"code":0,"indent":2,"parameters":[]},{"code":412,"indent":1,"parameters":[]},{"code":111,"indent":1,"parameters":[1,3,0,3,0]},{"code":231,"indent":2,"parameters":[3,"key_up",0,0,385,20,100,100,255,0]},{"code":111,"indent":2,"parameters":[11,"up"]},{"code":235,"indent":3,"parameters":[3]},{"code":250,"indent":3,"parameters":[{"name":"Pollen","volume":90,"pitch":100,"pan":0}]},{"code":122,"indent":3,"parameters":[5,5,2,0,200]},{"code":232,"indent":3,"parameters":[2,0,0,1,4,5,100,100,255,0,30,true]},{"code":122,"indent":3,"parameters":[2,2,1,0,1]},{"code":122,"indent":3,"parameters":[3,3,0,0,0]},{"code":0,"indent":3,"parameters":[]},{"code":412,"indent":2,"parameters":[]},{"code":0,"indent":2,"parameters":[]},{"code":412,"indent":1,"parameters":[]},{"code":111,"indent":1,"parameters":[1,2,0,3,0]},{"code":122,"indent":2,"parameters":[2,2,0,0,0]},{"code":113,"indent":2,"parameters":[]},{"code":0,"indent":2,"parameters":[]},{"code":412,"indent":1,"parameters":[]},{"code":0,"indent":1,"parameters":[]},{"code":413,"indent":0,"parameters":[]},{"code":356,"indent":0,"parameters":["ILB7_Timer stop"]},{"code":250,"indent":0,"parameters":[{"name":"Applause1","volume":90,"pitch":100,"pan":0}]},{"code":101,"indent":0,"parameters":["",0,1,1]},{"code":401,"indent":0,"parameters":["Done!"]},{"code":401,"indent":0,"parameters":["Your time: \\V[25]"]},{"code":118,"indent":0,"parameters":["skipped"]},{"code":235,"indent":0,"parameters":[1]},{"code":235,"indent":0,"parameters":[2]},{"code":235,"indent":0,"parameters":[3]},{"code":0,"indent":0,"parameters":[]}],"name":"soup_minigame","switchId":1,"trigger":0},
{"id":20,"list":[{"code":122,"indent":0,"parameters":[2,2,0,0,0]},{"code":231,"indent":0,"parameters":[1,"floor_tiles",0,0,48,12,100,100,255,0]},{"code":117,"indent":0,"parameters":[5]},{"code":231,"indent":0,"parameters":[3,"spray_bottle",0,0,10,230,100,100,255,0]},{"code":231,"indent":0,"parameters":[4,"sponge",0,0,300,200,100,100,255,0]},{"code":101,"indent":0,"parameters":["",0,1,1]},{"code":401,"indent":0,"parameters":["Clean the stains according to the onscreen directions."]},{"code":230,"indent":0,"parameters":[15]},{"code":122,"indent":0,"parameters":[6,6,0,0,0]},{"code":122,"indent":0,"parameters":[7,7,0,0,0]},{"code":356,"indent":0,"parameters":["ILB7_Timer start"]},{"code":112,"indent":0,"parameters":[]},{"code":111,"indent":1,"parameters":[11,"cancel"]},{"code":101,"indent":2,"parameters":["",0,1,1]},{"code":401,"indent":2,"parameters":["Are you sure you want to skip this minigame?"]},{"code":102,"indent":2,"parameters":[["Yes","No"],1,0,1,0]},{"code":402,"indent":2,"parameters":[0,"Yes"]},{"code":119,"indent":3,"parameters":["skipped"]},{"code":0,"indent":3,"parameters":[]},{"code":402,"indent":2,"parameters":[1,"No"]},{"code":0,"indent":3,"parameters":[]},{"code":404,"indent":2,"parameters":[]},{"code":0,"indent":2,"parameters":[]},{"code":412,"indent":1,"parameters":[]},{"code":111,"indent":1,"parameters":[1,7,0,1,0]},{"code":231,"indent":2,"parameters":[5,"key_left",0,0,55,300,100,100,255,0]},{"code":111,"indent":2,"parameters":[11,"left"]},{"code":235,"indent":3,"parameters":[5]},{"code":250,"indent":3,"parameters":[{"name":"Evasion1","volume":90,"pitch":100,"pan":0}]},{"code":232,"indent":3,"parameters":[4,0,0,0,140,250,100,100,255,0,30,true]},{"code":122,"indent":3,"parameters":[2,2,1,0,1]},{"code":111,"indent":3,"parameters":[1,2,0,20,0]},{"code":113,"indent":4,"parameters":[]},{"code":0,"indent":4,"parameters":[]},{"code":412,"indent":3,"parameters":[]},{"code":117,"indent":3,"parameters":[5]},{"code":117,"indent":3,"parameters":[6]},{"code":0,"indent":3,"parameters":[]},{"code":412,"indent":2,"parameters":[]},{"code":0,"indent":2,"parameters":[]},{"code":412,"indent":1,"parameters":[]},{"code":111,"indent":1,"parameters":[1,7,0,2,0]},{"code":231,"indent":2,"parameters":[5,"key_right",0,0,700,300,100,100,255,0]},{"code":111,"indent":2,"parameters":[11,"right"]},{"code":235,"indent":3,"parameters":[5]},{"code":250,"indent":3,"parameters":[{"name":"Evasion1","volume":90,"pitch":100,"pan":0}]},{"code":232,"indent":3,"parameters":[4,0,0,0,640,250,100,100,255,0,30,true]},{"code":122,"indent":3,"parameters":[2,2,1,0,1]},{"code":111,"indent":3,"parameters":[1,2,0,20,0]},{"code":113,"indent":4,"parameters":[]},{"code":0,"indent":4,"parameters":[]},{"code":412,"indent":3,"parameters":[]},{"code":117,"indent":3,"parameters":[5]},{"code":117,"indent":3,"parameters":[6]},{"code":0,"indent":3,"parameters":[]},{"code":412,"indent":2,"parameters":[]},{"code":0,"indent":2,"parameters":[]},{"code":412,"indent":1,"parameters":[]},{"code":111,"indent":1,"parameters":[1,7,0,3,0]},{"code":231,"indent":2,"parameters":[5,"key_up",0,0,385,20,100,100,255,0]},{"code":111,"indent":2,"parameters":[11,"up"]},{"code":235,"indent":3,"parameters":[5]},{"code":250,"indent":3,"parameters":[{"name":"Evasion1","volume":90,"pitch":100,"pan":0}]},{"code":232,"indent":3,"parameters":[4,0,0,0,350,50,100,100,255,0,30,true]},{"code":122,"indent":3,"parameters":[2,2,1,0,1]},{"code":111,"indent":3,"parameters":[1,2,0,20,0]},{"code":113,"indent":4,"parameters":[]},{"code":0,"indent":4,"parameters":[]},{"code":412,"indent":3,"parameters":[]},{"code":117,"indent":3,"parameters":[5]},{"code":117,"indent":3,"parameters":[6]},{"code":0,"indent":3,"parameters":[]},{"code":412,"indent":2,"parameters":[]},{"code":0,"indent":2,"parameters":[]},{"code":412,"indent":1,"parameters":[]},{"code":111,"indent":1,"parameters":[1,7,0,4,0]},{"code":231,"indent":2,"parameters":[5,"key_down",0,0,385,565,100,100,255,0]},{"code":111,"indent":2,"parameters":[11,"down"]},{"code":235,"indent":3,"parameters":[5]},{"code":250,"indent":3,"parameters":[{"name":"Evasion1","volume":90,"pitch":100,"pan":0}]},{"code":232,"indent":3,"parameters":[4,0,0,0,350,500,100,100,255,0,30,true]},{"code":122,"indent":3,"parameters":[2,2,1,0,1]},{"code":111,"indent":3,"parameters":[1,2,0,20,0]},{"code":113,"indent":4,"parameters":[]},{"code":0,"indent":4,"parameters":[]},{"code":412,"indent":3,"parameters":[]},{"code":117,"indent":3,"parameters":[5]},{"code":117,"indent":3,"parameters":[6]},{"code":0,"indent":3,"parameters":[]},{"code":412,"indent":2,"parameters":[]},{"code":0,"indent":2,"parameters":[]},{"code":412,"indent":1,"parameters":[]},{"code":111,"indent":1,"parameters":[1,7,0,0,0]},{"code":231,"indent":2,"parameters":[5,"key_enter",0,0,375,280,100,100,255,0]},{"code":111,"indent":2,"parameters":[11,"ok"]},{"code":235,"indent":3,"parameters":[5]},{"code":250,"indent":3,"parameters":[{"name":"Wind4","volume":90,"pitch":100,"pan":0}]},{"code":231,"indent":3,"parameters":[6,"spray",0,0,145,200,100,100,255,0]},{"code":232,"indent":3,"parameters":[6,0,0,0,400,200,100,100,255,0,30,true]},{"code":235,"indent":3,"parameters":[6]},{"code":122,"indent":3,"parameters":[2,2,1,0,1]},{"code":111,"indent":3,"parameters":[1,2,0,20,0]},{"code":113,"indent":4,"parameters":[]},{"code":0,"indent":4,"parameters":[]},{"code":412,"indent":3,"parameters":[]},{"code":117,"indent":3,"parameters":[5]},{"code":117,"indent":3,"parameters":[6]},{"code":0,"indent":3,"parameters":[]},{"code":412,"indent":2,"parameters":[]},{"code":0,"indent":2,"parameters":[]},{"code":412,"indent":1,"parameters":[]},{"code":0,"indent":1,"parameters":[]},{"code":413,"indent":0,"parameters":[]},{"code":356,"indent":0,"parameters":["ILB7_Timer stop"]},{"code":235,"indent":0,"parameters":[2]},{"code":250,"indent":0,"parameters":[{"name":"Applause1","volume":90,"pitch":100,"pan":0}]},{"code":101,"indent":0,"parameters":["",0,1,1]},{"code":401,"indent":0,"parameters":["Done!"]},{"code":401,"indent":0,"parameters":["Your time: \\V[25]"]},{"code":118,"indent":0,"parameters":["skipped"]},{"code":235,"indent":0,"parameters":[2]},{"code":235,"indent":0,"parameters":[1]},{"code":235,"indent":0,"parameters":[3]},{"code":235,"indent":0,"parameters":[4]},{"code":235,"indent":0,"parameters":[5]},{"code":0,"indent":0,"parameters":[]}],"name":"shiori_minigame","switchId":1,"trigger":0},
{"id":21,"list":[{"code":117,"indent":0,"parameters":[22]},{"code":122,"indent":0,"parameters":[2,2,0,0,0]},{"code":122,"indent":0,"parameters":[14,14,0,0,0]},{"code":122,"indent":0,"parameters":[15,15,0,0,0]},{"code":356,"indent":0,"parameters":["ILB7_NonBlockingMessageXY 0 500 center"]},{"code":231,"indent":0,"parameters":[1,"heart",0,0,50,300,100,100,255,0]},{"code":231,"indent":0,"parameters":[2,"heart",0,0,250,300,100,100,255,1]},{"code":231,"indent":0,"parameters":[3,"heart",0,0,450,300,100,100,255,1]},{"code":231,"indent":0,"parameters":[4,"heart",0,0,650,300,100,100,255,1]},{"code":231,"indent":0,"parameters":[5,"heart",0,0,850,300,100,100,255,1]},{"code":101,"indent":0,"parameters":["",0,1,1]},{"code":401,"indent":0,"parameters":["Perform chest compressions by pressing ENTER"]},{"code":401,"indent":0,"parameters":["when a heart coming from the right of the screen"]},{"code":401,"indent":0,"parameters":["overlaps with the stationary heart on the left"]},{"code":401,"indent":0,"parameters":["at a rate of around 100 beats per minute."]},{"code":356,"indent":0,"parameters":["ILB7_Timer start"]},{"code":112,"indent":0,"parameters":[]},{"code":122,"indent":1,"parameters":[3,3,0,0,0]},{"code":231,"indent":1,"parameters":[2,"heart",0,0,250,300,100,100,255,1]},{"code":231,"indent":1,"parameters":[3,"heart",0,0,450,300,100,100,255,1]},{"code":231,"indent":1,"parameters":[4,"heart",0,0,650,300,100,100,255,1]},{"code":231,"indent":1,"parameters":[5,"heart",0,0,850,300,100,100,255,1]},{"code":232,"indent":1,"parameters":[2,0,0,0,50,300,100,100,255,1,36,false]},{"code":232,"indent":1,"parameters":[3,0,0,0,250,300,100,100,255,1,36,false]},{"code":232,"indent":1,"parameters":[4,0,0,0,450,300,100,100,255,1,36,false]},{"code":232,"indent":1,"parameters":[5,0,0,0,650,300,100,100,255,1,36,false]},{"code":230,"indent":1,"parameters":[16]},{"code":112,"indent":1,"parameters":[]},{"code":111,"indent":2,"parameters":[11,"cancel"]},{"code":101,"indent":3,"parameters":["",0,1,1]},{"code":401,"indent":3,"parameters":["Are you sure you want to skip this minigame?"]},{"code":102,"indent":3,"parameters":[["Yes","No"],1,0,1,0]},{"code":402,"indent":3,"parameters":[0,"Yes"]},{"code":119,"indent":4,"parameters":["skipped"]},{"code":0,"indent":4,"parameters":[]},{"code":402,"indent":3,"parameters":[1,"No"]},{"code":0,"indent":4,"parameters":[]},{"code":404,"indent":3,"parameters":[]},{"code":0,"indent":3,"parameters":[]},{"code":412,"indent":2,"parameters":[]},{"code":111,"indent":2,"parameters":[11,"ok"]},{"code":250,"indent":3,"parameters":[{"name":"Dog","volume":90,"pitch":150,"pan":0}]},{"code":231,"indent":3,"parameters":[1,"heart",0,0,65,315,80,80,255,0]},{"code":111,"indent":3,"parameters":[1,3,1,12,3]},{"code":356,"indent":4,"parameters":["ILB7_NonBlockingMessage Fuwawa: Too slow, Moco-chan!"]},{"code":122,"indent":4,"parameters":[14,14,1,0,1]},{"code":0,"indent":4,"parameters":[]},{"code":411,"indent":3,"parameters":[]},{"code":111,"indent":4,"parameters":[1,3,1,13,4]},{"code":356,"indent":5,"parameters":["ILB7_NonBlockingMessage Fuwawa: Too fast, Moco-chan!"]},{"code":122,"indent":5,"parameters":[15,15,1,0,1]},{"code":0,"indent":5,"parameters":[]},{"code":411,"indent":4,"parameters":[]},{"code":122,"indent":5,"parameters":[2,2,1,0,1]},{"code":356,"indent":5,"parameters":["ILB7_NonBlockingMessage Fuwawa: Good! (\\V[2]/\\V[11])"]},{"code":0,"indent":5,"parameters":[]},{"code":412,"indent":4,"parameters":[]},{"code":0,"indent":4,"parameters":[]},{"code":412,"indent":3,"parameters":[]},{"code":113,"indent":3,"parameters":[]},{"code":0,"indent":3,"parameters":[]},{"code":411,"indent":2,"parameters":[]},{"code":231,"indent":3,"parameters":[1,"heart",0,0,50,300,100,100,255,0]},{"code":0,"indent":3,"parameters":[]},{"code":412,"indent":2,"parameters":[]},{"code":122,"indent":2,"parameters":[3,3,1,0,1]},{"code":230,"indent":2,"parameters":[1]},{"code":0,"indent":2,"parameters":[]},{"code":413,"indent":1,"parameters":[]},{"code":111,"indent":1,"parameters":[1,2,1,11,0]},{"code":113,"indent":2,"parameters":[]},{"code":0,"indent":2,"parameters":[]},{"code":412,"indent":1,"parameters":[]},{"code":0,"indent":1,"parameters":[]},{"code":413,"indent":0,"parameters":[]},{"code":356,"indent":0,"parameters":["ILB7_Timer stop"]},{"code":250,"indent":0,"parameters":[{"name":"Applause1","volume":90,"pitch":100,"pan":0}]},{"code":101,"indent":0,"parameters":["",0,1,1]},{"code":401,"indent":0,"parameters":["Done! Your results are:"]},{"code":401,"indent":0,"parameters":["Too fast: \\V[14], too slow: \\V[15]."]},{"code":401,"indent":0,"parameters":["Your time: \\V[25]"]},{"code":118,"indent":0,"parameters":["skipped"]},{"code":235,"indent":0,"parameters":[1]},{"code":235,"indent":0,"parameters":[2]},{"code":235,"indent":0,"parameters":[3]},{"code":235,"indent":0,"parameters":[4]},{"code":235,"indent":0,"parameters":[5]},{"code":356,"indent":0,"parameters":["ILB7_NonBlockingMessageClose"]},{"code":0,"indent":0,"parameters":[]}],"name":"cpr_minigame","switchId":1,"trigger":0},
{"id":22,"list":[{"code":111,"indent":0,"parameters":[1,10,0,1,0]},{"code":122,"indent":1,"parameters":[11,11,0,0,15]},{"code":122,"indent":1,"parameters":[12,12,0,0,23]},{"code":122,"indent":1,"parameters":[13,13,0,0,16]},{"code":0,"indent":1,"parameters":[]},{"code":412,"indent":0,"parameters":[]},{"code":111,"indent":0,"parameters":[1,10,0,2,0]},{"code":122,"indent":1,"parameters":[11,11,0,0,20]},{"code":122,"indent":1,"parameters":[12,12,0,0,22]},{"code":122,"indent":1,"parameters":[13,13,0,0,17]},{"code":0,"indent":1,"parameters":[]},{"code":412,"indent":0,"parameters":[]},{"code":111,"indent":0,"parameters":[1,10,0,3,0]},{"code":122,"indent":1,"parameters":[11,11,0,0,30]},{"code":122,"indent":1,"parameters":[12,12,0,0,22]},{"code":122,"indent":1,"parameters":[13,13,0,0,18]},{"code":0,"indent":1,"parameters":[]},{"code":412,"indent":0,"parameters":[]},{"code":111,"indent":0,"parameters":[1,10,0,4,0]},{"code":122,"indent":1,"parameters":[11,11,0,0,50]},{"code":122,"indent":1,"parameters":[12,12,0,0,21]},{"code":122,"indent":1,"parameters":[13,13,0,0,19]},{"code":0,"indent":1,"parameters":[]},{"code":412,"indent":0,"parameters":[]},{"code":111,"indent":0,"parameters":[1,10,0,5,0]},{"code":122,"indent":1,"parameters":[11,11,0,0,100]},{"code":122,"indent":1,"parameters":[12,12,0,0,20]},{"code":122,"indent":1,"parameters":[13,13,0,0,20]},{"code":0,"indent":1,"parameters":[]},{"code":412,"indent":0,"parameters":[]},{"code":0,"indent":0,"parameters":[]}],"name":"cpr_set_params","switchId":1,"trigger":0},
{"id":23,"list":[{"code":117,"indent":0,"parameters":[27]},{"code":126,"indent":0,"parameters":[2,0,0,1]},{"code":126,"indent":0,"parameters":[3,0,0,1]},{"code":121,"indent":0,"parameters":[11,14,1]},{"code":121,"indent":0,"parameters":[12,12,0]},{"code":122,"indent":0,"parameters":[18,18,0,0,2999]},{"code":122,"indent":0,"parameters":[21,21,0,0,2000]},{"code":117,"indent":0,"parameters":[9]},{"code":129,"indent":0,"parameters":[2,0,false]},{"code":129,"indent":0,"parameters":[1,1,false]},{"code":129,"indent":0,"parameters":[3,1,false]},{"code":129,"indent":0,"parameters":[4,1,false]},{"code":129,"indent":0,"parameters":[5,1,false]},{"code":129,"indent":0,"parameters":[6,1,false]},{"code":211,"indent":0,"parameters":[1]},{"code":201,"indent":0,"parameters":[0,4,10,6,2,0]},{"code":281,"indent":0,"parameters":[0]},{"code":0,"indent":0,"parameters":[]}],"name":"nerissa_start","switchId":1,"trigger":0},
{"id":24,"list":[{"code":230,"indent":0,"parameters":[30]},{"code":0,"indent":0,"parameters":[]}],"name":"standard_wait","switchId":1,"trigger":0},
{"id":25,"list":[{"code":101,"indent":0,"parameters":["",0,1,1]},{"code":401,"indent":0,"parameters":["Koseki Bijou, I can’t believe you never had a crush on"]},{"code":401,"indent":0,"parameters":["Kovu."]},{"code":401,"indent":0,"parameters":[" - Bae"]},{"code":101,"indent":0,"parameters":["Actor1",2,0,2]},{"code":401,"indent":0,"parameters":["Hakos Baelz..."]},{"code":0,"indent":0,"parameters":[]}],"name":"bae_letter","switchId":1,"trigger":0},
{"id":26,"list":[{"code":101,"indent":0,"parameters":["",0,1,1]},{"code":401,"indent":0,"parameters":["I promise that I will cheat on you."]},{"code":401,"indent":0,"parameters":["I will get new wives every single new day."]},{"code":401,"indent":0,"parameters":[" - Ollie"]},{"code":0,"indent":0,"parameters":[]}],"name":"ollie_bandage","switchId":1,"trigger":0},
{"id":27,"list":[{"code":126,"indent":0,"parameters":[1,1,0,1]},{"code":126,"indent":0,"parameters":[2,1,0,1]},{"code":126,"indent":0,"parameters":[3,1,0,1]},{"code":126,"indent":0,"parameters":[4,1,0,1]},{"code":126,"indent":0,"parameters":[5,1,0,1]},{"code":126,"indent":0,"parameters":[6,1,0,4]},{"code":126,"indent":0,"parameters":[7,1,0,1]},{"code":126,"indent":0,"parameters":[8,1,0,1]},{"code":126,"indent":0,"parameters":[11,1,0,1]},{"code":126,"indent":0,"parameters":[12,1,0,1]},{"code":126,"indent":0,"parameters":[13,1,0,1]},{"code":126,"indent":0,"parameters":[14,1,0,1]},{"code":126,"indent":0,"parameters":[15,1,0,1]},{"code":126,"indent":0,"parameters":[16,1,0,2]},{"code":126,"indent":0,"parameters":[17,1,0,1]},{"code":126,"indent":0,"parameters":[18,1,0,1]},{"code":0,"indent":0,"parameters":[]}],"name":"remove_items","switchId":1,"trigger":0},
{"id":28,"list":[{"code":117,"indent":0,"parameters":[36]},{"code":201,"indent":0,"parameters":[0,8,9,6,8,0]},{"code":281,"indent":0,"parameters":[0]},{"code":0,"indent":0,"parameters":[]}],"name":"shiori_start","switchId":1,"trigger":0},
{"id":29,"list":[{"code":122,"indent":0,"parameters":[18,18,2,0,1]},{"code":122,"indent":0,"parameters":[21,21,1,0,1]},{"code":0,"indent":0,"parameters":[]}],"name":"progress_story","switchId":1,"trigger":0},
{"id":30,"list":[{"code":117,"indent":0,"parameters":[27]},{"code":126,"indent":0,"parameters":[1,0,0,1]},{"code":121,"indent":0,"parameters":[11,14,1]},{"code":121,"indent":0,"parameters":[13,13,0]},{"code":122,"indent":0,"parameters":[18,18,0,0,3999]},{"code":122,"indent":0,"parameters":[21,21,0,0,3000]},{"code":117,"indent":0,"parameters":[10]},{"code":129,"indent":0,"parameters":[3,0,false]},{"code":129,"indent":0,"parameters":[1,1,false]},{"code":129,"indent":0,"parameters":[2,1,false]},{"code":129,"indent":0,"parameters":[4,1,false]},{"code":129,"indent":0,"parameters":[5,1,false]},{"code":129,"indent":0,"parameters":[6,1,false]},{"code":211,"indent":0,"parameters":[1]},{"code":201,"indent":0,"parameters":[0,7,8,8,8,0]},{"code":281,"indent":0,"parameters":[0]},{"code":0,"indent":0,"parameters":[]}],"name":"biboo_start","switchId":1,"trigger":0},
{"id":31,"list":[{"code":250,"indent":0,"parameters":[{"name":"Move1","pan":0,"pitch":100,"volume":90}]},{"code":0,"indent":0,"parameters":[]}],"name":"move_sound","switchId":1,"trigger":0},
{"id":32,"list":[{"code":250,"indent":0,"parameters":[{"name":"Door1","volume":90,"pitch":100,"pan":0}]},{"code":0,"indent":0,"parameters":[]}],"name":"door_sound","switchId":1,"trigger":0},
{"id":33,"list":[{"code":241,"indent":0,"parameters":[{"name":"Battle1","volume":90,"pitch":100,"pan":0}]},{"code":0,"indent":0,"parameters":[]}],"name":"chase_bgm","switchId":1,"trigger":0},
{"id":34,"list":[{"code":250,"indent":0,"parameters":[{"name":"Miss","volume":90,"pitch":100,"pan":0}]},{"code":0,"indent":0,"parameters":[]}],"name":"baloon_sound","switchId":1,"trigger":0},
{"id":35,"list":[{"code":122,"indent":0,"parameters":[24,24,1,0,1]},{"code":111,"indent":0,"parameters":[1,24,0,5,0]},{"code":250,"indent":1,"parameters":[{"name":"Damage3","volume":90,"pitch":100,"pan":0}]},{"code":213,"indent":1,"parameters":[10,6,false]},{"code":205,"indent":1,"parameters":[10,{"list":[{"code":29,"parameters":[5],"indent":null},{"code":0}],"repeat":false,"skippable":false,"wait":true}]},{"code":505,"indent":1,"parameters":[{"code":29,"parameters":[5],"indent":null}]},{"code":0,"indent":1,"parameters":[]},{"code":412,"indent":0,"parameters":[]},{"code":111,"indent":0,"parameters":[1,24,0,10,0]},{"code":250,"indent":1,"parameters":[{"name":"Damage3","volume":90,"pitch":100,"pan":0}]},{"code":213,"indent":1,"parameters":[10,6,false]},{"code":205,"indent":1,"parameters":[10,{"list":[{"code":29,"parameters":[4],"indent":null},{"code":0}],"repeat":false,"skippable":false,"wait":true}]},{"code":505,"indent":1,"parameters":[{"code":29,"parameters":[4],"indent":null}]},{"code":0,"indent":1,"parameters":[]},{"code":412,"indent":0,"parameters":[]},{"code":111,"indent":0,"parameters":[1,24,0,15,0]},{"code":250,"indent":1,"parameters":[{"name":"Damage3","volume":90,"pitch":100,"pan":0}]},{"code":213,"indent":1,"parameters":[10,6,false]},{"code":205,"indent":1,"parameters":[10,{"list":[{"code":29,"parameters":[3],"indent":null},{"code":0}],"repeat":false,"skippable":false,"wait":true}]},{"code":505,"indent":1,"parameters":[{"code":29,"parameters":[3],"indent":null}]},{"code":0,"indent":1,"parameters":[]},{"code":412,"indent":0,"parameters":[]},{"code":111,"indent":0,"parameters":[1,24,0,20,0]},{"code":250,"indent":1,"parameters":[{"name":"Damage3","volume":90,"pitch":100,"pan":0}]},{"code":213,"indent":1,"parameters":[10,6,false]},{"code":205,"indent":1,"parameters":[10,{"list":[{"code":29,"parameters":[2],"indent":null},{"code":0}],"repeat":false,"skippable":false,"wait":true}]},{"code":505,"indent":1,"parameters":[{"code":29,"parameters":[2],"indent":null}]},{"code":0,"indent":1,"parameters":[]},{"code":412,"indent":0,"parameters":[]},{"code":111,"indent":0,"parameters":[1,24,0,25,0]},{"code":250,"indent":1,"parameters":[{"name":"Damage3","volume":90,"pitch":100,"pan":0}]},{"code":213,"indent":1,"parameters":[10,6,false]},{"code":205,"indent":1,"parameters":[10,{"list":[{"code":29,"parameters":[1],"indent":null},{"code":0}],"repeat":false,"skippable":false,"wait":true}]},{"code":505,"indent":1,"parameters":[{"code":29,"parameters":[1],"indent":null}]},{"code":0,"indent":1,"parameters":[]},{"code":412,"indent":0,"parameters":[]},{"code":0,"indent":0,"parameters":[]}],"name":"biboo_got_away","switchId":1,"trigger":0},
{"id":36,"list":[{"code":117,"indent":0,"parameters":[27]},{"code":126,"indent":0,"parameters":[8,0,0,1]},{"code":126,"indent":0,"parameters":[11,0,0,1]},{"code":121,"indent":0,"parameters":[11,14,1]},{"code":121,"indent":0,"parameters":[11,11,0]},{"code":122,"indent":0,"parameters":[18,18,0,0,1999]},{"code":122,"indent":0,"parameters":[21,21,0,0,1000]},{"code":117,"indent":0,"parameters":[8]},{"code":129,"indent":0,"parameters":[1,0,false]},{"code":129,"indent":0,"parameters":[2,1,false]},{"code":129,"indent":0,"parameters":[3,1,false]},{"code":129,"indent":0,"parameters":[4,1,false]},{"code":129,"indent":0,"parameters":[5,1,false]},{"code":129,"indent":0,"parameters":[6,1,false]},{"code":211,"indent":0,"parameters":[1]},{"code":0,"indent":0,"parameters":[]}],"name":"set_shiori_route_params","switchId":1,"trigger":0},
{"id":37,"list":[{"code":250,"indent":0,"parameters":[{"name":"Decision2","volume":90,"pitch":100,"pan":0}]},{"code":117,"indent":0,"parameters":[9]},{"code":101,"indent":0,"parameters":["Actor1",1,0,2]},{"code":401,"indent":0,"parameters":["Hey, Shiori!"]},{"code":401,"indent":0,"parameters":["What’s up?"]},{"code":117,"indent":0,"parameters":[8]},{"code":101,"indent":0,"parameters":["Actor1",0,0,2]},{"code":401,"indent":0,"parameters":["Hi, Rissa."]},{"code":401,"indent":0,"parameters":["Could you come over right now?"]},{"code":401,"indent":0,"parameters":["I will need to ask you a favor once you’re"]},{"code":401,"indent":0,"parameters":["here."]},{"code":117,"indent":0,"parameters":[9]},{"code":101,"indent":0,"parameters":["Actor1",1,0,2]},{"code":401,"indent":0,"parameters":["Mhm. Of course."]},{"code":401,"indent":0,"parameters":["Anything for my beloved Shiorin!"]},{"code":401,"indent":0,"parameters":["I will be there in an instant."]},{"code":117,"indent":0,"parameters":[8]},{"code":101,"indent":0,"parameters":["Actor1",0,0,2]},{"code":401,"indent":0,"parameters":["Cool, I’m waiting for you then."]},{"code":117,"indent":0,"parameters":[9]},{"code":101,"indent":0,"parameters":["Actor1",1,0,2]},{"code":401,"indent":0,"parameters":["Love you, baby girl."]},{"code":117,"indent":0,"parameters":[8]},{"code":101,"indent":0,"parameters":["Actor1",0,0,2]},{"code":401,"indent":0,"parameters":["Okay, see ya."]},{"code":250,"indent":0,"parameters":[{"name":"Decision2","volume":90,"pitch":100,"pan":0}]},{"code":0,"indent":0,"parameters":[]}],"name":"shiori_nerissa_phone_conversation","switchId":1,"trigger":0},
{"id":38,"list":[{"code":101,"indent":0,"parameters":["",0,1,1]},{"code":401,"indent":0,"parameters":["Are you sure you want to reset this minigame?"]},{"code":102,"indent":0,"parameters":[["Yes","No"],1,0,1,0]},{"code":402,"indent":0,"parameters":[0,"Yes"]},{"code":223,"indent":1,"parameters":[[-255,-255,-255,0],1,false]},{"code":111,"indent":1,"parameters":[1,21,0,1006,0]},{"code":117,"indent":2,"parameters":[39]},{"code":0,"indent":2,"parameters":[]},{"code":412,"indent":1,"parameters":[]},{"code":223,"indent":1,"parameters":[[0,0,0,0],1,false]},{"code":0,"indent":1,"parameters":[]},{"code":402,"indent":0,"parameters":[1,"No"]},{"code":0,"indent":1,"parameters":[]},{"code":404,"indent":0,"parameters":[]},{"code":0,"indent":0,"parameters":[]}],"name":"minigame_reset","switchId":1,"trigger":0},
{"id":39,"list":[{"code":121,"indent":0,"parameters":[3,3,0]},{"code":117,"indent":0,"parameters":[36]},{"code":122,"indent":0,"parameters":[18,18,0,0,1993]},{"code":122,"indent":0,"parameters":[21,21,0,0,1006]},{"code":122,"indent":0,"parameters":[24,24,0,0,0]},{"code":201,"indent":0,"parameters":[0,7,8,5,2,0]},{"code":241,"indent":0,"parameters":[{"name":"Battle1","volume":90,"pitch":100,"pan":0}]},{"code":356,"indent":0,"parameters":["ILB7_Timer start"]},{"code":0,"indent":0,"parameters":[]}],"name":"set_up_shiori_chasing_biboo_minigame","switchId":1,"trigger":0},
{"id":40,"list":[{"code":101,"indent":0,"parameters":["",0,1,1]},{"code":401,"indent":0,"parameters":["Are you sure you want to go back to the minigames menu?"]},{"code":102,"indent":0,"parameters":[["Yes","No"],1,0,1,0]},{"code":402,"indent":0,"parameters":[0,"Yes"]},{"code":117,"indent":1,"parameters":[4]},{"code":0,"indent":1,"parameters":[]},{"code":402,"indent":0,"parameters":[1,"No"]},{"code":0,"indent":1,"parameters":[]},{"code":404,"indent":0,"parameters":[]},{"code":0,"indent":0,"parameters":[]}],"name":"back_to_minigames_menu","switchId":1,"trigger":0},
{"id":41,"list":[{"code":250,"indent":0,"parameters":[{"name":"Dog","volume":90,"pitch":150,"pan":0}]},{"code":230,"indent":0,"parameters":[15]},{"code":250,"indent":0,"parameters":[{"name":"Dog","volume":90,"pitch":150,"pan":0}]},{"code":230,"indent":0,"parameters":[60]},{"code":0,"indent":0,"parameters":[]}],"name":"bau_bau_sound","switchId":1,"trigger":0},
{"id":42,"list":[{"code":101,"indent":0,"parameters":["",0,0,2]},{"code":401,"indent":0,"parameters":["It's a bloodstain."]},{"code":111,"indent":0,"parameters":[1,21,0,1020,0]},{"code":101,"indent":1,"parameters":["Actor1",0,0,2]},{"code":401,"indent":1,"parameters":["This might be just a measly bloodstain,"]},{"code":401,"indent":1,"parameters":["but if the paramedics see it all sorts of"]},{"code":401,"indent":1,"parameters":["suspicions will arise."]},{"code":101,"indent":1,"parameters":["",0,1,1]},{"code":401,"indent":1,"parameters":["Clean it up?"]},{"code":102,"indent":1,"parameters":[["Yes","No"],1,0,1,0]},{"code":402,"indent":1,"parameters":[0,"Yes"]},{"code":117,"indent":2,"parameters":[20]},{"code":117,"indent":2,"parameters":[29]},{"code":242,"indent":2,"parameters":[5]},{"code":101,"indent":2,"parameters":["Actor1",0,0,2]},{"code":401,"indent":2,"parameters":["Okay, it's done!"]},{"code":205,"indent":2,"parameters":[-1,{"list":[{"code":3,"indent":null},{"code":3,"indent":null},{"code":3,"indent":null},{"code":3,"indent":null},{"code":3,"indent":null},{"code":4,"indent":null},{"code":4,"indent":null},{"code":0}],"repeat":false,"skippable":true,"wait":true}]},{"code":505,"indent":2,"parameters":[{"code":3,"indent":null}]},{"code":505,"indent":2,"parameters":[{"code":3,"indent":null}]},{"code":505,"indent":2,"parameters":[{"code":3,"indent":null}]},{"code":505,"indent":2,"parameters":[{"code":3,"indent":null}]},{"code":505,"indent":2,"parameters":[{"code":3,"indent":null}]},{"code":505,"indent":2,"parameters":[{"code":4,"indent":null}]},{"code":505,"indent":2,"parameters":[{"code":4,"indent":null}]},{"code":101,"indent":2,"parameters":["Actor1",0,0,2]},{"code":401,"indent":2,"parameters":["And I made it just in time!"]},{"code":117,"indent":2,"parameters":[32]},{"code":203,"indent":2,"parameters":[27,0,8,9,0]},{"code":117,"indent":2,"parameters":[29]},{"code":205,"indent":2,"parameters":[27,{"list":[{"code":4,"indent":null},{"code":18,"indent":null},{"code":15,"parameters":[15],"indent":0},{"code":17,"indent":null},{"code":15,"parameters":[15],"indent":0},{"code":18,"indent":null},{"code":15,"parameters":[15],"indent":null},{"code":17,"indent":null},{"code":0}],"repeat":false,"skippable":false,"wait":true}]},{"code":505,"indent":2,"parameters":[{"code":4,"indent":null}]},{"code":505,"indent":2,"parameters":[{"code":18,"indent":null}]},{"code":505,"indent":2,"parameters":[{"code":15,"parameters":[15],"indent":0}]},{"code":505,"indent":2,"parameters":[{"code":17,"indent":null}]},{"code":505,"indent":2,"parameters":[{"code":15,"parameters":[15],"indent":0}]},{"code":505,"indent":2,"parameters":[{"code":18,"indent":null}]},{"code":505,"indent":2,"parameters":[{"code":15,"parameters":[15],"indent":null}]},{"code":505,"indent":2,"parameters":[{"code":17,"indent":null}]},{"code":205,"indent":2,"parameters":[-1,{"list":[{"code":17,"indent":null},{"code":0}],"repeat":false,"skippable":false,"wait":true}]},{"code":505,"indent":2,"parameters":[{"code":17,"indent":null}]},{"code":101,"indent":2,"parameters":["Actor1",0,0,2]},{"code":401,"indent":2,"parameters":["Oh, hello there."]},{"code":401,"indent":2,"parameters":["May I help you?"]},{"code":205,"indent":2,"parameters":[27,{"list":[{"code":18,"indent":null},{"code":0}],"repeat":false,"skippable":false,"wait":true}]},{"code":505,"indent":2,"parameters":[{"code":18,"indent":null}]},{"code":117,"indent":2,"parameters":[7]},{"code":101,"indent":2,"parameters":["",0,0,2]},{"code":401,"indent":2,"parameters":["\\N<Paramedic>Hi, we received a call that there was a person here in"]},{"code":401,"indent":2,"parameters":["need of medical assistance due to getting stabbed."]},{"code":117,"indent":2,"parameters":[8]},{"code":101,"indent":2,"parameters":["Actor1",0,0,2]},{"code":401,"indent":2,"parameters":["Oh, nyo, that sounds scawy."]},{"code":401,"indent":2,"parameters":["But there is no\\.\\fibody\\fi like that in here."]},{"code":401,"indent":2,"parameters":["It must be my neighbors playing pranks on"]},{"code":401,"indent":2,"parameters":["me again."]},{"code":101,"indent":2,"parameters":["Actor1",0,0,2]},{"code":401,"indent":2,"parameters":["They do these kinds of things all the time."]},{"code":117,"indent":2,"parameters":[7]},{"code":101,"indent":2,"parameters":["",0,0,2]},{"code":401,"indent":2,"parameters":["\\N<Paramedic>It seems so."]},{"code":401,"indent":2,"parameters":["Sorry for the intrusion, and have a nice day."]},{"code":117,"indent":2,"parameters":[8]},{"code":101,"indent":2,"parameters":["Actor1",0,0,2]},{"code":401,"indent":2,"parameters":["Have a nice day too."]},{"code":205,"indent":2,"parameters":[27,{"list":[{"code":1,"indent":null},{"code":0}],"repeat":false,"skippable":false,"wait":true}]},{"code":505,"indent":2,"parameters":[{"code":1,"indent":null}]},{"code":117,"indent":2,"parameters":[32]},{"code":117,"indent":2,"parameters":[29]},{"code":203,"indent":2,"parameters":[21,0,8,9,0]},{"code":203,"indent":2,"parameters":[22,0,9,9,0]},{"code":230,"indent":2,"parameters":[60]},{"code":117,"indent":2,"parameters":[32]},{"code":117,"indent":2,"parameters":[29]},{"code":205,"indent":2,"parameters":[22,{"list":[{"code":4,"indent":null},{"code":4,"indent":null},{"code":0}],"repeat":false,"skippable":false,"wait":false}]},{"code":505,"indent":2,"parameters":[{"code":4,"indent":null}]},{"code":505,"indent":2,"parameters":[{"code":4,"indent":null}]},{"code":205,"indent":2,"parameters":[21,{"list":[{"code":4,"indent":null},{"code":4,"indent":null},{"code":0}],"repeat":false,"skippable":false,"wait":true}]},{"code":505,"indent":2,"parameters":[{"code":4,"indent":null}]},{"code":505,"indent":2,"parameters":[{"code":4,"indent":null}]},{"code":117,"indent":2,"parameters":[34]},{"code":213,"indent":2,"parameters":[22,1,false]},{"code":213,"indent":2,"parameters":[21,1,true]},{"code":205,"indent":2,"parameters":[21,{"list":[{"code":17,"indent":null},{"code":15,"parameters":[15],"indent":null},{"code":0}],"repeat":false,"skippable":false,"wait":true}]},{"code":505,"indent":2,"parameters":[{"code":17,"indent":null}]},{"code":505,"indent":2,"parameters":[{"code":15,"parameters":[15],"indent":null}]},{"code":205,"indent":2,"parameters":[22,{"list":[{"code":18,"indent":null},{"code":15,"parameters":[15],"indent":null},{"code":0}],"repeat":false,"skippable":false,"wait":true}]},{"code":505,"indent":2,"parameters":[{"code":18,"indent":null}]},{"code":505,"indent":2,"parameters":[{"code":15,"parameters":[15],"indent":null}]},{"code":205,"indent":2,"parameters":[21,{"list":[{"code":19,"indent":null},{"code":15,"parameters":[15],"indent":null},{"code":0}],"repeat":false,"skippable":false,"wait":true}]},{"code":505,"indent":2,"parameters":[{"code":19,"indent":null}]},{"code":505,"indent":2,"parameters":[{"code":15,"parameters":[15],"indent":null}]},{"code":205,"indent":2,"parameters":[22,{"list":[{"code":19,"indent":null},{"code":15,"parameters":[15],"indent":null},{"code":0}],"repeat":false,"skippable":false,"wait":true}]},{"code":505,"indent":2,"parameters":[{"code":19,"indent":null}]},{"code":505,"indent":2,"parameters":[{"code":15,"parameters":[15],"indent":null}]},{"code":117,"indent":2,"parameters":[12]},{"code":101,"indent":2,"parameters":["Actor1",4,0,2]},{"code":401,"indent":2,"parameters":["Where did he go?"]},{"code":117,"indent":2,"parameters":[8]},{"code":101,"indent":2,"parameters":["Actor1",0,0,2]},{"code":401,"indent":2,"parameters":["You don’t have to worry about that."]},{"code":205,"indent":2,"parameters":[22,{"list":[{"code":18,"indent":null},{"code":0}],"repeat":false,"skippable":false,"wait":false}]},{"code":505,"indent":2,"parameters":[{"code":18,"indent":null}]},{"code":205,"indent":2,"parameters":[21,{"list":[{"code":18,"indent":null},{"code":0}],"repeat":false,"skippable":false,"wait":true}]},{"code":505,"indent":2,"parameters":[{"code":18,"indent":null}]},{"code":117,"indent":2,"parameters":[12]},{"code":101,"indent":2,"parameters":["Actor1",4,0,2]},{"code":401,"indent":2,"parameters":["Oh..."]},{"code":117,"indent":2,"parameters":[11]},{"code":101,"indent":2,"parameters":["Actor1",3,0,2]},{"code":401,"indent":2,"parameters":["O-okay."]},{"code":111,"indent":2,"parameters":[4,4,0]},{"code":117,"indent":3,"parameters":[11]},{"code":101,"indent":3,"parameters":["Actor1",3,0,2]},{"code":401,"indent":3,"parameters":["(I guess he’s dead.)"]},{"code":117,"indent":3,"parameters":[12]},{"code":101,"indent":3,"parameters":["Actor1",4,0,2]},{"code":401,"indent":3,"parameters":["(And got disposed of.)"]},{"code":0,"indent":3,"parameters":[]},{"code":412,"indent":2,"parameters":[]},{"code":203,"indent":2,"parameters":[18,0,9,9,0]},{"code":203,"indent":2,"parameters":[17,0,8,9,0]},{"code":117,"indent":2,"parameters":[32]},{"code":117,"indent":2,"parameters":[29]},{"code":205,"indent":2,"parameters":[17,{"list":[{"code":4,"indent":null},{"code":0}],"repeat":false,"skippable":false,"wait":false}]},{"code":505,"indent":2,"parameters":[{"code":4,"indent":null}]},{"code":205,"indent":2,"parameters":[18,{"list":[{"code":4,"indent":null},{"code":0}],"repeat":false,"skippable":false,"wait":true}]},{"code":505,"indent":2,"parameters":[{"code":4,"indent":null}]},{"code":117,"indent":2,"parameters":[10]},{"code":101,"indent":2,"parameters":["Actor1",2,0,2]},{"code":401,"indent":2,"parameters":["Maybe we \\fican\\fi get away with this!"]},{"code":117,"indent":2,"parameters":[8]},{"code":101,"indent":2,"parameters":["Actor1",0,0,2]},{"code":401,"indent":2,"parameters":["Yeah! "]},{"code":205,"indent":2,"parameters":[17,{"list":[{"code":18,"indent":null},{"code":0}],"repeat":false,"skippable":false,"wait":false}]},{"code":505,"indent":2,"parameters":[{"code":18,"indent":null}]},{"code":205,"indent":2,"parameters":[18,{"list":[{"code":18,"indent":null},{"code":0}],"repeat":false,"skippable":false,"wait":true}]},{"code":505,"indent":2,"parameters":[{"code":18,"indent":null}]},{"code":117,"indent":2,"parameters":[10]},{"code":101,"indent":2,"parameters":["Actor1",2,0,2]},{"code":401,"indent":2,"parameters":["I’m sorry I tried to call the police on"]},{"code":401,"indent":2,"parameters":["you earlier, Shiori."]},{"code":117,"indent":2,"parameters":[8]},{"code":101,"indent":2,"parameters":["Actor1",0,0,2]},{"code":401,"indent":2,"parameters":["It’s okay."]},{"code":401,"indent":2,"parameters":["There, there."]},{"code":213,"indent":2,"parameters":[-1,13,false]},{"code":213,"indent":2,"parameters":[17,13,false]},{"code":213,"indent":2,"parameters":[18,13,false]},{"code":213,"indent":2,"parameters":[21,13,false]},{"code":213,"indent":2,"parameters":[22,13,true]},{"code":101,"indent":2,"parameters":["Actor1",0,0,2]},{"code":401,"indent":2,"parameters":["And let’s not talk about this incident ever"]},{"code":401,"indent":2,"parameters":["again!"]},{"code":401,"indent":2,"parameters":["It's shiover!"]},{"code":213,"indent":2,"parameters":[-1,13,false]},{"code":213,"indent":2,"parameters":[17,13,false]},{"code":213,"indent":2,"parameters":[18,13,false]},{"code":213,"indent":2,"parameters":[21,13,false]},{"code":213,"indent":2,"parameters":[22,13,true]},{"code":221,"indent":2,"parameters":[]},{"code":101,"indent":2,"parameters":["",0,1,1]},{"code":401,"indent":2,"parameters":[""]},{"code":401,"indent":2,"parameters":["                       The end\\|?"]},{"code":108,"indent":2,"parameters":["Shiori route clear"]},{"code":117,"indent":2,"parameters":[45]},{"code":0,"indent":2,"parameters":[]},{"code":402,"indent":1,"parameters":[1,"No"]},{"code":0,"indent":2,"parameters":[]},{"code":404,"indent":1,"parameters":[]},{"code":0,"indent":1,"parameters":[]},{"code":412,"indent":0,"parameters":[]},{"code":0,"indent":0,"parameters":[]}],"name":"bloodstain","switchId":1,"trigger":0},
{"id":43,"list":[{"code":101,"indent":0,"parameters":["",0,0,2]},{"code":401,"indent":0,"parameters":["Clean it up?"]},{"code":102,"indent":0,"parameters":[["Yes","No"],1,0,2,0]},{"code":402,"indent":0,"parameters":[0,"Yes"]},{"code":122,"indent":1,"parameters":[19,19,0,0,0]},{"code":122,"indent":1,"parameters":[20,20,0,0,0]},{"code":250,"indent":1,"parameters":[{"name":"Miss","volume":90,"pitch":100,"pan":0}]},{"code":0,"indent":1,"parameters":[]},{"code":402,"indent":0,"parameters":[1,"No"]},{"code":0,"indent":1,"parameters":[]},{"code":404,"indent":0,"parameters":[]},{"code":0,"indent":0,"parameters":[]}],"name":"poo","switchId":1,"trigger":0},
{"id":44,"list":[{"code":129,"indent":0,"parameters":[1,0,false]},{"code":129,"indent":0,"parameters":[2,1,false]},{"code":129,"indent":0,"parameters":[3,1,false]},{"code":129,"indent":0,"parameters":[4,1,false]},{"code":129,"indent":0,"parameters":[5,1,false]},{"code":129,"indent":0,"parameters":[6,1,false]},{"code":129,"indent":0,"parameters":[2,0,false]},{"code":129,"indent":0,"parameters":[3,0,false]},{"code":129,"indent":0,"parameters":[4,0,false]},{"code":129,"indent":0,"parameters":[5,0,false]},{"code":0,"indent":0,"parameters":[]}],"name":"add_party_members","switchId":1,"trigger":0},
{"id":45,"list":[{"code":281,"indent":0,"parameters":[1]},{"code":211,"indent":0,"parameters":[0]},{"code":201,"indent":0,"parameters":[0,1,0,0,0,0]},{"code":117,"indent":0,"parameters":[44]},{"code":352,"indent":0,"parameters":[]},{"code":222,"indent":0,"parameters":[]},{"code":0,"indent":0,"parameters":[]}],"name":"route_clear","switchId":1,"trigger":0},
{"id":46,"list":[{"code":117,"indent":0,"parameters":[9]},{"code":101,"indent":0,"parameters":["Actor1",1,0,2]},{"code":401,"indent":0,"parameters":["Hiya darlings, my name is-"]},{"code":101,"indent":0,"parameters":["Actor1",1,0,2]},{"code":401,"indent":0,"parameters":["..."]},{"code":111,"indent":0,"parameters":[4,2,0]},{"code":205,"indent":1,"parameters":[-1,{"list":[{"code":17,"indent":null},{"code":15,"parameters":[60],"indent":null},{"code":19,"indent":null},{"code":0}],"repeat":false,"skippable":false,"wait":true}]},{"code":505,"indent":1,"parameters":[{"code":17,"indent":null}]},{"code":505,"indent":1,"parameters":[{"code":15,"parameters":[60],"indent":null}]},{"code":505,"indent":1,"parameters":[{"code":19,"indent":null}]},{"code":0,"indent":1,"parameters":[]},{"code":411,"indent":0,"parameters":[]},{"code":205,"indent":1,"parameters":[18,{"list":[{"code":17,"indent":null},{"code":15,"parameters":[60],"indent":null},{"code":19,"indent":null},{"code":0}],"repeat":false,"skippable":false,"wait":true}]},{"code":505,"indent":1,"parameters":[{"code":17,"indent":null}]},{"code":505,"indent":1,"parameters":[{"code":15,"parameters":[60],"indent":null}]},{"code":505,"indent":1,"parameters":[{"code":19,"indent":null}]},{"code":0,"indent":1,"parameters":[]},{"code":412,"indent":0,"parameters":[]},{"code":101,"indent":0,"parameters":["Actor1",1,0,2]},{"code":401,"indent":0,"parameters":["Eh?"]},{"code":117,"indent":0,"parameters":[24]},{"code":101,"indent":0,"parameters":["Actor1",1,0,2]},{"code":401,"indent":0,"parameters":["What is going on?"]},{"code":117,"indent":0,"parameters":[8]},{"code":117,"indent":0,"parameters":[24]},{"code":101,"indent":0,"parameters":["Actor1",0,0,2]},{"code":401,"indent":0,"parameters":["Oh, hi, Rissa!"]},{"code":117,"indent":0,"parameters":[24]},{"code":117,"indent":0,"parameters":[9]},{"code":101,"indent":0,"parameters":["Actor1",1,0,2]},{"code":401,"indent":0,"parameters":["He’s dead!"]},{"code":401,"indent":0,"parameters":["What have you done, Shiori?"]},{"code":117,"indent":0,"parameters":[8]},{"code":101,"indent":0,"parameters":["Actor1",0,0,2]},{"code":401,"indent":0,"parameters":["It’s fine!"]},{"code":111,"indent":0,"parameters":[4,1,0]},{"code":205,"indent":1,"parameters":[-1,{"list":[{"code":3,"indent":null},{"code":3,"indent":null},{"code":3,"indent":null},{"code":4,"indent":null},{"code":16,"indent":null},{"code":0}],"repeat":false,"skippable":false,"wait":true}]},{"code":505,"indent":1,"parameters":[{"code":3,"indent":null}]},{"code":505,"indent":1,"parameters":[{"code":3,"indent":null}]},{"code":505,"indent":1,"parameters":[{"code":3,"indent":null}]},{"code":505,"indent":1,"parameters":[{"code":4,"indent":null}]},{"code":505,"indent":1,"parameters":[{"code":16,"indent":null}]},{"code":0,"indent":1,"parameters":[]},{"code":411,"indent":0,"parameters":[]},{"code":205,"indent":1,"parameters":[29,{"list":[{"code":3,"indent":null},{"code":3,"indent":null},{"code":3,"indent":null},{"code":4,"indent":null},{"code":16,"indent":null},{"code":0}],"repeat":false,"skippable":false,"wait":true}]},{"code":505,"indent":1,"parameters":[{"code":3,"indent":null}]},{"code":505,"indent":1,"parameters":[{"code":3,"indent":null}]},{"code":505,"indent":1,"parameters":[{"code":3,"indent":null}]},{"code":505,"indent":1,"parameters":[{"code":4,"indent":null}]},{"code":505,"indent":1,"parameters":[{"code":16,"indent":null}]},{"code":0,"indent":1,"parameters":[]},{"code":412,"indent":0,"parameters":[]},{"code":101,"indent":0,"parameters":["Actor1",0,0,2]},{"code":401,"indent":0,"parameters":["We can still talk to Dimitri AI!"]},{"code":117,"indent":0,"parameters":[9]},{"code":101,"indent":0,"parameters":["Actor1",1,0,2]},{"code":401,"indent":0,"parameters":["W-What?"]},{"code":401,"indent":0,"parameters":["No that’s... that’s not what I meant."]},{"code":117,"indent":0,"parameters":[8]},{"code":101,"indent":0,"parameters":["Actor1",0,0,2]},{"code":401,"indent":0,"parameters":["Anyway, I need you to help me hide this"]},{"code":401,"indent":0,"parameters":["\\fibody\\fi."]},{"code":401,"indent":0,"parameters":["Someone might come looking for him and I"]},{"code":401,"indent":0,"parameters":["don’t want to be caught red-handed."]},{"code":117,"indent":0,"parameters":[9]},{"code":101,"indent":0,"parameters":["Actor1",1,0,2]},{"code":401,"indent":0,"parameters":["Umm... ok."]},{"code":401,"indent":0,"parameters":["But how do we do it?"]},{"code":117,"indent":0,"parameters":[8]},{"code":101,"indent":0,"parameters":["Actor1",0,0,2]},{"code":401,"indent":0,"parameters":["I don’t know."]},{"code":401,"indent":0,"parameters":["Let’s ask Dimitri!"]},{"code":111,"indent":0,"parameters":[4,1,0]},{"code":205,"indent":1,"parameters":[-1,{"list":[{"code":19,"indent":null},{"code":0}],"repeat":false,"skippable":false,"wait":true}]},{"code":505,"indent":1,"parameters":[{"code":19,"indent":null}]},{"code":0,"indent":1,"parameters":[]},{"code":411,"indent":0,"parameters":[]},{"code":205,"indent":1,"parameters":[29,{"list":[{"code":19,"indent":null},{"code":0}],"repeat":false,"skippable":false,"wait":true}]},{"code":505,"indent":1,"parameters":[{"code":19,"indent":null}]},{"code":0,"indent":1,"parameters":[]},{"code":412,"indent":0,"parameters":[]},{"code":101,"indent":0,"parameters":["Actor1",0,0,2]},{"code":401,"indent":0,"parameters":["How to hide a body, Dimitri?"]},{"code":401,"indent":0,"parameters":["I can’t get caught!"]},{"code":401,"indent":0,"parameters":["I have to protect our happy sugar life!"]},{"code":117,"indent":0,"parameters":[7]},{"code":101,"indent":0,"parameters":["",0,0,2]},{"code":401,"indent":0,"parameters":["\\N<Dimitri AI>Don’t."]},{"code":401,"indent":0,"parameters":["Call the authorities and turn yourself in."]},{"code":230,"indent":0,"parameters":[60]},{"code":250,"indent":0,"parameters":[{"name":"527726__lnab__typing-on-a-keyboard","volume":100,"pitch":100,"pan":0}]},{"code":230,"indent":0,"parameters":[90]},{"code":117,"indent":0,"parameters":[8]},{"code":101,"indent":0,"parameters":["Actor1",0,0,2]},{"code":401,"indent":0,"parameters":["Better ask Emomitri."]},{"code":117,"indent":0,"parameters":[7]},{"code":101,"indent":0,"parameters":["",0,0,2]},{"code":401,"indent":0,"parameters":["\\N<Emomitri AI>You could cut up the body into small pieces, mix it"]},{"code":401,"indent":0,"parameters":["with potting soil, and plant something in it."]},{"code":401,"indent":0,"parameters":["The body will be nowhere to be found and will quickly"]},{"code":401,"indent":0,"parameters":["end up absorbed into the soil, and later the plant."]},{"code":117,"indent":0,"parameters":[8]},{"code":101,"indent":0,"parameters":["Actor1",0,0,2]},{"code":401,"indent":0,"parameters":["Now we’re talking!"]},{"code":401,"indent":0,"parameters":["Okay, now, what is the best way to eat it?"]},{"code":117,"indent":0,"parameters":[7]},{"code":101,"indent":0,"parameters":["",0,0,2]},{"code":401,"indent":0,"parameters":["\\N<Emomitri AI>Eating human flesh is dangerous, especially if raw or"]},{"code":401,"indent":0,"parameters":["undercooked."]},{"code":401,"indent":0,"parameters":["Your cooking is literally poison, Shiori."]},{"code":117,"indent":0,"parameters":[8]},{"code":101,"indent":0,"parameters":["Actor1",0,0,2]},{"code":401,"indent":0,"parameters":["Never mind."]},{"code":117,"indent":0,"parameters":[9]},{"code":101,"indent":0,"parameters":["Actor1",1,0,2]},{"code":401,"indent":0,"parameters":["So... that's what we're going to do?"]},{"code":111,"indent":0,"parameters":[4,1,0]},{"code":205,"indent":1,"parameters":[-1,{"list":[{"code":16,"indent":null},{"code":0}],"repeat":false,"skippable":false,"wait":true}]},{"code":505,"indent":1,"parameters":[{"code":16,"indent":null}]},{"code":0,"indent":1,"parameters":[]},{"code":411,"indent":0,"parameters":[]},{"code":205,"indent":1,"parameters":[29,{"list":[{"code":16,"indent":null},{"code":0}],"repeat":false,"skippable":false,"wait":true}]},{"code":505,"indent":1,"parameters":[{"code":16,"indent":null}]},{"code":0,"indent":1,"parameters":[]},{"code":412,"indent":0,"parameters":[]},{"code":117,"indent":0,"parameters":[8]},{"code":101,"indent":0,"parameters":["Actor1",0,0,2]},{"code":401,"indent":0,"parameters":["Yeah, but before that, can you go check up"]},{"code":401,"indent":0,"parameters":["on Biboo?"]},{"code":401,"indent":0,"parameters":["She’s in the streaming room."]},{"code":117,"indent":0,"parameters":[9]},{"code":101,"indent":0,"parameters":["Actor1",1,0,2]},{"code":401,"indent":0,"parameters":["Wait, Biboo’s here too?"]},{"code":117,"indent":0,"parameters":[8]},{"code":101,"indent":0,"parameters":["Actor1",0,0,2]},{"code":401,"indent":0,"parameters":["Yeah, I’m getting a little worried about"]},{"code":401,"indent":0,"parameters":["her."]},{"code":401,"indent":0,"parameters":["I knocked her out pretty hard."]},{"code":117,"indent":0,"parameters":[9]},{"code":101,"indent":0,"parameters":["Actor1",1,0,2]},{"code":401,"indent":0,"parameters":["Eh?"]},{"code":401,"indent":0,"parameters":["Wh-Why did you have to knock her out?"]},{"code":117,"indent":0,"parameters":[8]},{"code":101,"indent":0,"parameters":["Actor1",0,0,2]},{"code":401,"indent":0,"parameters":["Because she was trying to call the police."]},{"code":117,"indent":0,"parameters":[24]},{"code":117,"indent":0,"parameters":[9]},{"code":101,"indent":0,"parameters":["Actor1",1,0,2]},{"code":401,"indent":0,"parameters":["Oh, that... that makes sense."]},{"code":401,"indent":0,"parameters":["Sure, I’ll go check if she’s fine."]},{"code":117,"indent":0,"parameters":[8]},{"code":101,"indent":0,"parameters":["Actor1",0,0,2]},{"code":401,"indent":0,"parameters":["Thanks, and I’m going to..."]},{"code":111,"indent":0,"parameters":[4,1,0]},{"code":205,"indent":1,"parameters":[-1,{"list":[{"code":17,"indent":null},{"code":15,"parameters":[60],"indent":null},{"code":0}],"repeat":false,"skippable":false,"wait":true}]},{"code":505,"indent":1,"parameters":[{"code":17,"indent":null}]},{"code":505,"indent":1,"parameters":[{"code":15,"parameters":[60],"indent":null}]},{"code":0,"indent":1,"parameters":[]},{"code":411,"indent":0,"parameters":[]},{"code":205,"indent":1,"parameters":[29,{"list":[{"code":17,"indent":null},{"code":15,"parameters":[60],"indent":null},{"code":0}],"repeat":false,"skippable":false,"wait":true}]},{"code":505,"indent":1,"parameters":[{"code":17,"indent":null}]},{"code":505,"indent":1,"parameters":[{"code":15,"parameters":[60],"indent":null}]},{"code":0,"indent":1,"parameters":[]},{"code":412,"indent":0,"parameters":[]},{"code":117,"indent":0,"parameters":[9]},{"code":101,"indent":0,"parameters":["Actor1",1,0,2]},{"code":401,"indent":0,"parameters":["Is something wrong?"]},{"code":117,"indent":0,"parameters":[8]},{"code":101,"indent":0,"parameters":["Actor1",0,0,2]},{"code":401,"indent":0,"parameters":["I wonder how this looks under a microscope."]},{"code":117,"indent":0,"parameters":[9]},{"code":101,"indent":0,"parameters":["Actor1",1,0,2]},{"code":401,"indent":0,"parameters":["..."]},{"code":117,"indent":0,"parameters":[8]},{"code":111,"indent":0,"parameters":[4,1,0]},{"code":205,"indent":1,"parameters":[-1,{"list":[{"code":1,"indent":null},{"code":2,"indent":null},{"code":2,"indent":null},{"code":2,"indent":null},{"code":0}],"repeat":false,"skippable":false,"wait":true}]},{"code":505,"indent":1,"parameters":[{"code":1,"indent":null}]},{"code":505,"indent":1,"parameters":[{"code":2,"indent":null}]},{"code":505,"indent":1,"parameters":[{"code":2,"indent":null}]},{"code":505,"indent":1,"parameters":[{"code":2,"indent":null}]},{"code":0,"indent":1,"parameters":[]},{"code":411,"indent":0,"parameters":[]},{"code":205,"indent":1,"parameters":[29,{"list":[{"code":1,"indent":null},{"code":2,"indent":null},{"code":2,"indent":null},{"code":2,"indent":null},{"code":0}],"repeat":false,"skippable":false,"wait":true}]},{"code":505,"indent":1,"parameters":[{"code":1,"indent":null}]},{"code":505,"indent":1,"parameters":[{"code":2,"indent":null}]},{"code":505,"indent":1,"parameters":[{"code":2,"indent":null}]},{"code":505,"indent":1,"parameters":[{"code":2,"indent":null}]},{"code":0,"indent":1,"parameters":[]},{"code":412,"indent":0,"parameters":[]},{"code":250,"indent":0,"parameters":[{"name":"Evasion1","volume":90,"pitch":100,"pan":0}]},{"code":117,"indent":0,"parameters":[24]},{"code":250,"indent":0,"parameters":[{"name":"Item1","volume":90,"pitch":100,"pan":0}]},{"code":111,"indent":0,"parameters":[4,1,0]},{"code":121,"indent":1,"parameters":[15,15,0]},{"code":126,"indent":1,"parameters":[7,0,0,1]},{"code":101,"indent":1,"parameters":["",0,1,1]},{"code":401,"indent":1,"parameters":["You obtained \\C[1]Dimitri's blood sample\\C[0]."]},{"code":205,"indent":1,"parameters":[-1,{"list":[{"code":16,"indent":null},{"code":0}],"repeat":false,"skippable":false,"wait":true}]},{"code":505,"indent":1,"parameters":[{"code":16,"indent":null}]},{"code":0,"indent":1,"parameters":[]},{"code":411,"indent":0,"parameters":[]},{"code":101,"indent":1,"parameters":["",0,1,1]},{"code":401,"indent":1,"parameters":["Shiori obtained \\C[1]Dimitri's blood sample\\C[0]."]},{"code":205,"indent":1,"parameters":[29,{"list":[{"code":16,"indent":null},{"code":0}],"repeat":false,"skippable":false,"wait":true}]},{"code":505,"indent":1,"parameters":[{"code":16,"indent":null}]},{"code":0,"indent":1,"parameters":[]},{"code":412,"indent":0,"parameters":[]},{"code":101,"indent":0,"parameters":["Actor1",0,0,2]},{"code":401,"indent":0,"parameters":["I guess it doesn’t make sense to clean the"]},{"code":401,"indent":0,"parameters":["kitchen floor right now when we're going to"]},{"code":401,"indent":0,"parameters":["make a big mess while cutting up the body"]},{"code":401,"indent":0,"parameters":["anyway."]},{"code":101,"indent":0,"parameters":["Actor1",0,0,2]},{"code":401,"indent":0,"parameters":["I'll bring the plant here first."]},{"code":401,"indent":0,"parameters":["I left it in the library upstairs."]},{"code":117,"indent":0,"parameters":[9]},{"code":101,"indent":0,"parameters":["Actor1",1,0,2]},{"code":401,"indent":0,"parameters":["O-Okay."]},{"code":401,"indent":0,"parameters":["Well then, I'm off to go check up on Biboo."]},{"code":117,"indent":0,"parameters":[8]},{"code":101,"indent":0,"parameters":["Actor1",0,0,2]},{"code":401,"indent":0,"parameters":["Okay!"]},{"code":111,"indent":0,"parameters":[4,2,0]},{"code":205,"indent":1,"parameters":[-1,{"list":[{"code":16,"indent":null},{"code":0}],"repeat":false,"skippable":false,"wait":true}]},{"code":505,"indent":1,"parameters":[{"code":16,"indent":null}]},{"code":0,"indent":1,"parameters":[]},{"code":411,"indent":0,"parameters":[]},{"code":205,"indent":1,"parameters":[18,{"list":[{"code":16,"indent":null},{"code":0}],"repeat":false,"skippable":false,"wait":true}]},{"code":505,"indent":1,"parameters":[{"code":16,"indent":null}]},{"code":0,"indent":1,"parameters":[]},{"code":412,"indent":0,"parameters":[]},{"code":117,"indent":0,"parameters":[9]},{"code":101,"indent":0,"parameters":["Actor1",1,0,2]},{"code":401,"indent":0,"parameters":["I guess the Inkwell Residence is now a"]},{"code":401,"indent":0,"parameters":["murder house."]},{"code":117,"indent":0,"parameters":[8]},{"code":101,"indent":0,"parameters":["Actor1",0,0,2]},{"code":401,"indent":0,"parameters":["Not too far off my childhood home."]},{"code":111,"indent":0,"parameters":[4,2,0]},{"code":205,"indent":1,"parameters":[-1,{"list":[{"code":19,"indent":null},{"code":0}],"repeat":false,"skippable":false,"wait":false}]},{"code":505,"indent":1,"parameters":[{"code":19,"indent":null}]},{"code":0,"indent":1,"parameters":[]},{"code":411,"indent":0,"parameters":[]},{"code":205,"indent":1,"parameters":[18,{"list":[{"code":19,"indent":null},{"code":0}],"repeat":false,"skippable":false,"wait":false}]},{"code":505,"indent":1,"parameters":[{"code":19,"indent":null}]},{"code":0,"indent":1,"parameters":[]},{"code":412,"indent":0,"parameters":[]},{"code":117,"indent":0,"parameters":[34]},{"code":111,"indent":0,"parameters":[4,2,0]},{"code":213,"indent":1,"parameters":[-1,2,true]},{"code":0,"indent":1,"parameters":[]},{"code":411,"indent":0,"parameters":[]},{"code":213,"indent":1,"parameters":[18,2,true]},{"code":0,"indent":1,"parameters":[]},{"code":412,"indent":0,"parameters":[]},{"code":117,"indent":0,"parameters":[9]},{"code":101,"indent":0,"parameters":["Actor1",1,0,2]},{"code":401,"indent":0,"parameters":["Eh?"]},{"code":117,"indent":0,"parameters":[8]},{"code":101,"indent":0,"parameters":["Actor1",0,0,2]},{"code":401,"indent":0,"parameters":["It’s a joke. It’s a joke."]},{"code":401,"indent":0,"parameters":["I love my parents, I swear."]},{"code":117,"indent":0,"parameters":[9]},{"code":101,"indent":0,"parameters":["Actor1",1,0,2]},{"code":401,"indent":0,"parameters":["Oh, Shiori~n."]},{"code":0,"indent":0,"parameters":[]}],"name":"shiori_rissa_first_kitchen_convo","switchId":1,"trigger":0},
{"id":47,"list":[{"code":111,"indent":0,"parameters":[8,17]},{"code":111,"indent":1,"parameters":[0,18,0]},{"code":111,"indent":2,"parameters":[0,19,0]},{"code":101,"indent":3,"parameters":["Actor1",1,0,2]},{"code":401,"indent":3,"parameters":["Ok, I think I have all the ingredients now."]},{"code":401,"indent":3,"parameters":["Let's use the stove!"]},{"code":117,"indent":3,"parameters":[29]},{"code":0,"indent":3,"parameters":[]},{"code":412,"indent":2,"parameters":[]},{"code":0,"indent":2,"parameters":[]},{"code":412,"indent":1,"parameters":[]},{"code":0,"indent":1,"parameters":[]},{"code":412,"indent":0,"parameters":[]},{"code":0,"indent":0,"parameters":[]}],"name":"has_girl_dinner_ingredients","switchId":1,"trigger":0}
]